{
  "generated_at": "2026-06-15T12:57:49.248504",
  "profile_id": "reg-veneto",
  "profile_name": "Regulatory Affairs — Veneto",
  "total_jobs_analyzed": 39,
  "scoring": {
    "average": 16.4,
    "distribution": {
      "excellent": 0,
      "good": 3,
      "medium": 4,
      "low": 2,
      "irrelevant": 30
    },
    "top_jobs": [
      {
        "title": "Regulatory Affairs Manager - Biocidi e Fitofarmaci",
        "company": "NonStop Consulting",
        "score": 64,
        "site": "linkedin",
        "date_posted": null,
        "url": "https://www.linkedin.com/jobs/view/4421823097"
      },
      {
        "title": "Senior Regulatory Affairs Specialist",
        "company": "NEWCHEM SPA",
        "score": 60,
        "site": "linkedin",
        "date_posted": 1779840000000,
        "url": "https://www.linkedin.com/jobs/view/4413675692"
      },
      {
        "title": "REGULATORY SPECIALIST",
        "company": "Colorificio Paulin S.p.A.",
        "score": 60,
        "site": "linkedin",
        "date_posted": null,
        "url": "https://www.linkedin.com/jobs/view/4421952309"
      },
      {
        "title": "Senior International Regulatory Specialist",
        "company": "Orthofix",
        "score": 57,
        "site": "linkedin",
        "date_posted": 1779753600000,
        "url": "https://www.linkedin.com/jobs/view/4367239299"
      },
      {
        "title": "Senior quality assurance GMP",
        "company": "Adecco",
        "score": 49,
        "site": "linkedin",
        "date_posted": 1780012800000,
        "url": "https://www.linkedin.com/jobs/view/4417957067"
      },
      {
        "title": "RIF.3807: REGULATORY COMPLIANCE OFFICER  - SETTORE REFRIGERAZIONE INDUSTRIALE",
        "company": "Arethusa",
        "score": 48,
        "site": "linkedin",
        "date_posted": 1780012800000,
        "url": "https://www.linkedin.com/jobs/view/4412751752"
      },
      {
        "title": "PQ Persona Qualificata",
        "company": "MedicAir",
        "score": 43,
        "site": "linkedin",
        "date_posted": null,
        "url": "https://www.linkedin.com/jobs/view/4425755875"
      },
      {
        "title": "Opportunità di Lavoro – Categorie Protette (L.68/99)",
        "company": "Newpharm",
        "score": 20,
        "site": "indeed",
        "date_posted": 1779753600000,
        "url": "https://it.indeed.com/viewjob?jk=14f9f75c7dc1f613"
      },
      {
        "title": "Marketing Farmaceutico",
        "company": "ALMA LABORIS Business School",
        "score": 20,
        "site": "indeed",
        "date_posted": 1779753600000,
        "url": "https://it.indeed.com/viewjob?jk=54949be1bc94e8a8"
      },
      {
        "title": "Quality Assurance & Auditing Manager",
        "company": "Penta - Child Health Research",
        "score": 16,
        "site": "linkedin",
        "date_posted": null,
        "url": "https://www.linkedin.com/jobs/view/4428805774"
      },
      {
        "title": "Quality Assurance Manager",
        "company": "SteelcoBelimed Inc.",
        "score": 14,
        "site": "indeed",
        "date_posted": 1780617600000,
        "url": "https://it.indeed.com/viewjob?jk=14c367d68e50f917"
      },
      {
        "title": "Quality Assurance Specialist - Vicenza",
        "company": "Eurofins",
        "score": 12,
        "site": "linkedin",
        "date_posted": 1779840000000,
        "url": "https://www.linkedin.com/jobs/view/4419868821"
      },
      {
        "title": "Quality Assurance Specialist - Vicenza",
        "company": "Eurofins PSS Insourcing Solutions",
        "score": 12,
        "site": "linkedin",
        "date_posted": null,
        "url": "https://www.linkedin.com/jobs/view/4417215462"
      },
      {
        "title": "Quality Assurance Specialist",
        "company": "SteelcoBelimed Inc.",
        "score": 11,
        "site": "indeed",
        "date_posted": 1780617600000,
        "url": "https://it.indeed.com/viewjob?jk=3f0a52192415b8d9"
      },
      {
        "title": "Responsible Person",
        "company": "H.Essers",
        "score": 11,
        "site": "indeed",
        "date_posted": 1781222400000,
        "url": "https://it.indeed.com/viewjob?jk=c64dac7ebb3e0197"
      },
      {
        "title": "Specialist Onco-Haematology (Veneto e Trentino-Alto Adige)",
        "company": "GSK",
        "score": 10,
        "site": "linkedin",
        "date_posted": null,
        "url": "https://www.linkedin.com/jobs/view/4423643270"
      },
      {
        "title": "Specialist Onco-Haematology (Toscana Nord e Centro)",
        "company": "GSK",
        "score": 10,
        "site": "linkedin",
        "date_posted": null,
        "url": "https://www.linkedin.com/jobs/view/4423646083"
      },
      {
        "title": "Specialist Onco-Haematology (Lazio Nord, Umbria, Toscana Sud)",
        "company": "GSK",
        "score": 10,
        "site": "linkedin",
        "date_posted": null,
        "url": "https://www.linkedin.com/jobs/view/4423644152"
      },
      {
        "title": "meccanico auto",
        "company": "GPT AUTO SRLS",
        "score": 10,
        "site": "indeed",
        "date_posted": 1781481600000,
        "url": "https://it.indeed.com/viewjob?jk=13828fa0a66cba97"
      },
      {
        "title": "IT Manager ERP e Sistemi Informativi",
        "company": "Supporto HR",
        "score": 9,
        "site": "indeed",
        "date_posted": 1780617600000,
        "url": "https://it.indeed.com/viewjob?jk=b45fa836de244954"
      }
    ]
  },
  "filter_suggestions": {
    "add_relevant": [],
    "add_blacklist": [
      {
        "word": "quality",
        "count": 5,
        "reason": "Appare 5x in annunci a basso score"
      },
      {
        "word": "assurance",
        "count": 5,
        "reason": "Appare 5x in annunci a basso score"
      },
      {
        "word": "sistema",
        "count": 4,
        "reason": "Appare 4x in annunci a basso score"
      },
      {
        "word": "addetto",
        "count": 4,
        "reason": "Appare 4x in annunci a basso score"
      },
      {
        "word": "tecnico",
        "count": 3,
        "reason": "Appare 3x in annunci a basso score"
      }
    ],
    "review": []
  },
  "keyword_recommendations": [],
  "anomalies": [
    {
      "type": "new_jobs_ratio",
      "severity": "info",
      "message": "📊 Ultimo scan: 3/3 annunci da aziende nuove (100.0%)",
      "data": {
        "new": 3,
        "total": 3,
        "pct": 100.0
      }
    },
    {
      "type": "channel_shift",
      "severity": "low",
      "message": "📡 indeed: quota passata da 50% a 33% (-17pp)",
      "data": {
        "channel": "indeed",
        "old_pct": 50.0,
        "new_pct": 33.3
      }
    },
    {
      "type": "channel_shift",
      "severity": "low",
      "message": "📡 linkedin: quota passata da 50% a 67% (+17pp)",
      "data": {
        "channel": "linkedin",
        "old_pct": 50.0,
        "new_pct": 66.7
      }
    },
    {
      "type": "role_clusters",
      "severity": "info",
      "message": "🔬 Identificati 5 cluster di ruoli nel mercato",
      "data": {
        "clusters": [
          {
            "id": 0,
            "size": 20,
            "top_terms": [
              "specialist",
              "venezia",
              "haematology"
            ],
            "pct": 51.3
          },
          {
            "id": 2,
            "size": 6,
            "top_terms": [
              "quality",
              "assurance",
              "vicenza"
            ],
            "pct": 15.4
          },
          {
            "id": 1,
            "size": 5,
            "top_terms": [
              "addetto",
              "sistema",
              "operatore"
            ],
            "pct": 12.8
          },
          {
            "id": 3,
            "size": 5,
            "top_terms": [
              "regulatory",
              "specialist",
              "affairs"
            ],
            "pct": 12.8
          },
          {
            "id": 4,
            "size": 3,
            "top_terms": [
              "tecnico",
              "specialist",
              "vicenza"
            ],
            "pct": 7.7
          }
        ]
      }
    }
  ],
  "feedback_stats": {
    "total_votes": 14,
    "users": 1,
    "feedback_boost_active": true
  }
}