{
  "generated_at": "2026-04-26T08:14:08.403334",
  "profile_id": "msl-lombardia",
  "profile_name": "Medical Liaison — Lombardia",
  "total_jobs_analyzed": 171,
  "scoring": {
    "average": 27.1,
    "distribution": {
      "excellent": 0,
      "good": 3,
      "medium": 68,
      "low": 15,
      "irrelevant": 85
    },
    "top_jobs": [
      {
        "title": "Medical Advisor Biologics - Dermatology",
        "company": "Galderma",
        "score": 62,
        "site": "linkedin",
        "date_posted": null,
        "url": "https://www.linkedin.com/jobs/view/4380931992"
      },
      {
        "title": "Medical Advisor",
        "company": "Sobi - Swedish Orphan Biovitrum AB (publ)",
        "score": 62,
        "site": "linkedin",
        "date_posted": null,
        "url": "https://www.linkedin.com/jobs/view/4372114590"
      },
      {
        "title": "Clinical trial & medical affairs manager",
        "company": "Lionhealth Società Benefit (SB)",
        "score": 60,
        "site": "linkedin",
        "date_posted": null,
        "url": "https://www.linkedin.com/jobs/view/4402435466"
      },
      {
        "title": "Medical Affairs Director, Chronic & Prevention",
        "company": "Mölnlycke Health Care",
        "score": 59,
        "site": "linkedin",
        "date_posted": null,
        "url": "https://www.linkedin.com/jobs/view/4399510850"
      },
      {
        "title": "Medical Scientific Liaison (MSL) - Northern-Eastern Italy",
        "company": "Teva Pharmaceuticals",
        "score": 59,
        "site": "linkedin",
        "date_posted": null,
        "url": "https://www.linkedin.com/jobs/view/4381997937"
      },
      {
        "title": "Medical Monitor (Gastroenterology)",
        "company": "PSI CRO",
        "score": 58,
        "site": "linkedin",
        "date_posted": 1775692800000,
        "url": "https://www.linkedin.com/jobs/view/4398806622"
      },
      {
        "title": "REGULATORY AFFAIRS SPECIALIST",
        "company": "Andrea Poletti Group",
        "score": 58,
        "site": "linkedin",
        "date_posted": 1776902400000,
        "url": "https://www.linkedin.com/jobs/view/4405668983"
      },
      {
        "title": "unior Regulatory Affairs Specialist",
        "company": "BEAUTICON VALLEY Holding",
        "score": 58,
        "site": "linkedin",
        "date_posted": 1776988800000,
        "url": "https://www.linkedin.com/jobs/view/4403721850"
      },
      {
        "title": "Medical Affairs Clinician - Italy",
        "company": "Evolus",
        "score": 57,
        "site": "linkedin",
        "date_posted": null,
        "url": "https://www.linkedin.com/jobs/view/4342294307"
      },
      {
        "title": "Medical Advisor Junior",
        "company": "Neopharmed Gentili S.P.A.",
        "score": 57,
        "site": "linkedin",
        "date_posted": null,
        "url": "https://www.linkedin.com/jobs/view/4402522369"
      },
      {
        "title": "Junior Medical Advisor",
        "company": "KOLINPHARMA S.p.A",
        "score": 57,
        "site": "linkedin",
        "date_posted": null,
        "url": "https://www.linkedin.com/jobs/view/4403923357"
      },
      {
        "title": "(Associate) Medical Director - Rheumatology, EMEA",
        "company": "Thermo Fisher Scientific",
        "score": 57,
        "site": "indeed",
        "date_posted": 1776988800000,
        "url": "https://it.indeed.com/viewjob?jk=e4517f89fe8140ca"
      },
      {
        "title": "International Medical Science Liaison, Oncology",
        "company": "IQVIA",
        "score": 56,
        "site": "linkedin",
        "date_posted": 1775606400000,
        "url": "https://www.linkedin.com/jobs/view/4384494774"
      },
      {
        "title": "Medical Science Liaison Paediatric Oncology - Milan",
        "company": "Norgine",
        "score": 56,
        "site": "linkedin",
        "date_posted": 1775520000000,
        "url": "https://www.linkedin.com/jobs/view/4394781112"
      },
      {
        "title": "Hepatology - Medical Director",
        "company": "Medpace",
        "score": 56,
        "site": "linkedin",
        "date_posted": 1775347200000,
        "url": "https://www.linkedin.com/jobs/view/4331970390"
      },
      {
        "title": "Medical Director",
        "company": "Alexion Pharmaceuticals, Inc.",
        "score": 56,
        "site": "linkedin",
        "date_posted": null,
        "url": "https://www.linkedin.com/jobs/view/4402544242"
      },
      {
        "title": "Medical Director",
        "company": "EVERSANA INTOUCH",
        "score": 56,
        "site": "linkedin",
        "date_posted": 1776470400000,
        "url": "https://www.linkedin.com/jobs/view/4403598089"
      },
      {
        "title": "Scientific and Regulatory Affairs Manager",
        "company": "Henkel",
        "score": 56,
        "site": "indeed",
        "date_posted": 1776729600000,
        "url": "https://it.indeed.com/viewjob?jk=cfdd15acb40344cd"
      },
      {
        "title": "Medical Science Liaison (m/f/x) - Nephrology",
        "company": "CSL",
        "score": 56,
        "site": "linkedin",
        "date_posted": null,
        "url": "https://www.linkedin.com/jobs/view/4402807584"
      },
      {
        "title": "Dermatologist - Medical Director",
        "company": "Medpace",
        "score": 56,
        "site": "linkedin",
        "date_posted": null,
        "url": "https://www.linkedin.com/jobs/view/4331270944"
      }
    ]
  },
  "filter_suggestions": {
    "add_relevant": [],
    "add_blacklist": [
      {
        "word": "specialist",
        "count": 18,
        "reason": "Appare 18x in annunci a basso score"
      },
      {
        "word": "italy",
        "count": 11,
        "reason": "Appare 11x in annunci a basso score"
      },
      {
        "word": "project",
        "count": 8,
        "reason": "Appare 8x in annunci a basso score"
      },
      {
        "word": "engineer",
        "count": 8,
        "reason": "Appare 8x in annunci a basso score"
      },
      {
        "word": "senior",
        "count": 7,
        "reason": "Appare 7x in annunci a basso score"
      }
    ],
    "review": []
  },
  "keyword_recommendations": [
    {
      "keyword": "italy",
      "frequency": 6,
      "source": "parola frequente in titoli rilevanti",
      "confidence": 60
    },
    {
      "keyword": "medical scientific",
      "frequency": 2,
      "source": "bigram/trigram da titoli rilevanti",
      "confidence": 30
    },
    {
      "keyword": "director italy",
      "frequency": 2,
      "source": "bigram/trigram da titoli rilevanti",
      "confidence": 30
    }
  ],
  "anomalies": [
    {
      "type": "volume_drop",
      "severity": "high",
      "message": "Volume in calo: 6 annunci ultimo scan vs media 13 (-53%)",
      "data": {
        "current": 6,
        "avg": 12.7,
        "change_pct": -52.7
      }
    },
    {
      "type": "new_jobs_ratio",
      "severity": "info",
      "message": "📊 Ultimo scan: 1/6 annunci da aziende nuove (16.7%)",
      "data": {
        "new": 1,
        "total": 6,
        "pct": 16.7
      }
    },
    {
      "type": "channel_shift",
      "severity": "low",
      "message": "📡 indeed: quota passata da 43% a 17% (-26pp)",
      "data": {
        "channel": "indeed",
        "old_pct": 42.9,
        "new_pct": 16.7
      }
    },
    {
      "type": "channel_shift",
      "severity": "low",
      "message": "📡 linkedin: quota passata da 57% a 83% (+26pp)",
      "data": {
        "channel": "linkedin",
        "old_pct": 57.1,
        "new_pct": 83.3
      }
    },
    {
      "type": "role_clusters",
      "severity": "info",
      "message": "🔬 Identificati 5 cluster di ruoli nel mercato",
      "data": {
        "clusters": [
          {
            "id": 1,
            "size": 70,
            "top_terms": [
              "specialist",
              "engineer",
              "manager"
            ],
            "pct": 40.9
          },
          {
            "id": 4,
            "size": 35,
            "top_terms": [
              "medical",
              "director",
              "advisor"
            ],
            "pct": 20.5
          },
          {
            "id": 2,
            "size": 31,
            "top_terms": [
              "clinical",
              "research",
              "italy"
            ],
            "pct": 18.1
          },
          {
            "id": 0,
            "size": 23,
            "top_terms": [
              "regulatory",
              "affairs",
              "specialist"
            ],
            "pct": 13.5
          },
          {
            "id": 3,
            "size": 12,
            "top_terms": [
              "senior",
              "cra",
              "manager"
            ],
            "pct": 7.0
          }
        ]
      }
    }
  ],
  "feedback_stats": {
    "total_votes": 14,
    "users": 1,
    "feedback_boost_active": true
  }
}