{
  "generated_at": "2026-05-09T08:31:57.233148",
  "profile_id": "msl-lombardia",
  "profile_name": "Medical Liaison — Lombardia",
  "total_jobs_analyzed": 175,
  "scoring": {
    "average": 29.5,
    "distribution": {
      "excellent": 0,
      "good": 3,
      "medium": 85,
      "low": 9,
      "irrelevant": 78
    },
    "top_jobs": [
      {
        "title": "Medical Advisor",
        "company": "Sobi - Swedish Orphan Biovitrum AB (publ)",
        "score": 62,
        "site": "linkedin",
        "date_posted": 1776384000000,
        "url": "https://www.linkedin.com/jobs/view/4372114590"
      },
      {
        "title": "Medical Advisor Biologics - Dermatology",
        "company": "Galderma",
        "score": 62,
        "site": "linkedin",
        "date_posted": null,
        "url": "https://www.linkedin.com/jobs/view/4380931992"
      },
      {
        "title": "Clinical Development Medical Director (Associate Director)",
        "company": "Pfizer",
        "score": 60,
        "site": "linkedin",
        "date_posted": null,
        "url": "https://www.linkedin.com/jobs/view/4411264071"
      },
      {
        "title": "Medical Scientific Liaison (MSL) - Northern-Eastern Italy",
        "company": "Teva Pharmaceuticals",
        "score": 59,
        "site": "linkedin",
        "date_posted": 1776816000000,
        "url": "https://www.linkedin.com/jobs/view/4381997937"
      },
      {
        "title": "Medical Affairs Specialist",
        "company": "Tintinelli & CO S.R.L.",
        "score": 59,
        "site": "linkedin",
        "date_posted": null,
        "url": "https://www.linkedin.com/jobs/view/4405557111"
      },
      {
        "title": "Junior Medical Advisor",
        "company": "KOLINPHARMA S.p.A",
        "score": 58,
        "site": "linkedin",
        "date_posted": 1776729600000,
        "url": "https://www.linkedin.com/jobs/view/4403923357"
      },
      {
        "title": "Medical Monitor (Gastroenterology)",
        "company": "PSI CRO",
        "score": 58,
        "site": "linkedin",
        "date_posted": 1776643200000,
        "url": "https://www.linkedin.com/jobs/view/4401604991"
      },
      {
        "title": "Medical Advisor Lung Cancer",
        "company": "AstraZeneca",
        "score": 58,
        "site": "linkedin",
        "date_posted": null,
        "url": "https://www.linkedin.com/jobs/view/4412107301"
      },
      {
        "title": "Medical Director",
        "company": "EVERSANA INTOUCH",
        "score": 57,
        "site": "linkedin",
        "date_posted": 1776470400000,
        "url": "https://www.linkedin.com/jobs/view/4403598089"
      },
      {
        "title": "Dermatologist - Medical Director",
        "company": "Medpace",
        "score": 57,
        "site": "linkedin",
        "date_posted": null,
        "url": "https://www.linkedin.com/jobs/view/4331270944"
      },
      {
        "title": "Psychiatry - Medical Director",
        "company": "Medpace",
        "score": 57,
        "site": "linkedin",
        "date_posted": null,
        "url": "https://www.linkedin.com/jobs/view/4331940454"
      },
      {
        "title": "Hepatology - Medical Director",
        "company": "Medpace",
        "score": 57,
        "site": "linkedin",
        "date_posted": 1777161600000,
        "url": "https://www.linkedin.com/jobs/view/4331970390"
      },
      {
        "title": "Medical Affairs Clinician - Italy",
        "company": "Evolus",
        "score": 57,
        "site": "linkedin",
        "date_posted": null,
        "url": "https://www.linkedin.com/jobs/view/4342294307"
      },
      {
        "title": "Medical Science Liaison (m/f/x) - Nephrology",
        "company": "CSL",
        "score": 56,
        "site": "linkedin",
        "date_posted": 1776816000000,
        "url": "https://www.linkedin.com/jobs/view/4402807584"
      },
      {
        "title": "Medical Science Liaison Paediatric Oncology - Milan",
        "company": "Norgine",
        "score": 56,
        "site": "linkedin",
        "date_posted": null,
        "url": "https://www.linkedin.com/jobs/view/4394781112"
      },
      {
        "title": "Stage in Medical Affairs",
        "company": "Johnson & Johnson Innovative Medicine",
        "score": 56,
        "site": "linkedin",
        "date_posted": null,
        "url": "https://www.linkedin.com/jobs/view/4411652146"
      },
      {
        "title": "Clinical Research Associate, Site Management - Italy",
        "company": "IQVIA",
        "score": 56,
        "site": "linkedin",
        "date_posted": 1778025600000,
        "url": "https://www.linkedin.com/jobs/view/4409954292"
      },
      {
        "title": "Regulatory Affairs Specialist",
        "company": "Recordati S.p.A",
        "score": 56,
        "site": "indeed",
        "date_posted": 1778198400000,
        "url": "https://it.indeed.com/viewjob?jk=488fa890cbf8540a"
      },
      {
        "title": "Director, Medical Affairs LIVE Italy",
        "company": "Gilead Sciences",
        "score": 55,
        "site": "linkedin",
        "date_posted": null,
        "url": "https://www.linkedin.com/jobs/view/4374040619"
      },
      {
        "title": "Medical Communication Specialist Eucerin",
        "company": "Beiersdorf SpA",
        "score": 55,
        "site": "indeed",
        "date_posted": 1777248000000,
        "url": "https://it.indeed.com/viewjob?jk=d95821eeb3dac98c"
      }
    ]
  },
  "filter_suggestions": {
    "add_relevant": [],
    "add_blacklist": [
      {
        "word": "manager",
        "count": 25,
        "reason": "Appare 25x in annunci a basso score"
      },
      {
        "word": "senior",
        "count": 10,
        "reason": "Appare 10x in annunci a basso score"
      },
      {
        "word": "engineer",
        "count": 10,
        "reason": "Appare 10x in annunci a basso score"
      },
      {
        "word": "specialist",
        "count": 9,
        "reason": "Appare 9x in annunci a basso score"
      },
      {
        "word": "access",
        "count": 7,
        "reason": "Appare 7x in annunci a basso score"
      }
    ],
    "review": []
  },
  "keyword_recommendations": [
    {
      "keyword": "italy",
      "frequency": 8,
      "source": "parola frequente in titoli rilevanti",
      "confidence": 80
    },
    {
      "keyword": "international",
      "frequency": 4,
      "source": "parola frequente in titoli rilevanti",
      "confidence": 40
    },
    {
      "keyword": "medical scientific",
      "frequency": 2,
      "source": "bigram/trigram da titoli rilevanti",
      "confidence": 30
    },
    {
      "keyword": "international medical",
      "frequency": 2,
      "source": "bigram/trigram da titoli rilevanti",
      "confidence": 30
    },
    {
      "keyword": "client dedicated",
      "frequency": 2,
      "source": "bigram/trigram da titoli rilevanti",
      "confidence": 30
    },
    {
      "keyword": "lung cancer",
      "frequency": 2,
      "source": "bigram/trigram da titoli rilevanti",
      "confidence": 30
    },
    {
      "keyword": "emilia romagna",
      "frequency": 2,
      "source": "bigram/trigram da titoli rilevanti",
      "confidence": 30
    }
  ],
  "anomalies": [
    {
      "type": "new_jobs_ratio",
      "severity": "info",
      "message": "📊 Ultimo scan: 5/11 annunci da aziende nuove (45.5%)",
      "data": {
        "new": 5,
        "total": 11,
        "pct": 45.5
      }
    },
    {
      "type": "role_clusters",
      "severity": "info",
      "message": "🔬 Identificati 5 cluster di ruoli nel mercato",
      "data": {
        "clusters": [
          {
            "id": 0,
            "size": 72,
            "top_terms": [
              "manager",
              "specialist",
              "engineer"
            ],
            "pct": 41.1
          },
          {
            "id": 4,
            "size": 32,
            "top_terms": [
              "medical",
              "director",
              "italy"
            ],
            "pct": 18.3
          },
          {
            "id": 1,
            "size": 28,
            "top_terms": [
              "clinical",
              "associate",
              "research"
            ],
            "pct": 16.0
          },
          {
            "id": 2,
            "size": 28,
            "top_terms": [
              "regulatory",
              "affairs",
              "specialist"
            ],
            "pct": 16.0
          },
          {
            "id": 3,
            "size": 15,
            "top_terms": [
              "senior",
              "cra",
              "ai"
            ],
            "pct": 8.6
          }
        ]
      }
    }
  ],
  "feedback_stats": {
    "total_votes": 14,
    "users": 1,
    "feedback_boost_active": true
  }
}