[
  {
    "id":"in-f64affe1a0aaca3f",
    "site":"indeed",
    "job_url":"https:\/\/it.indeed.com\/viewjob?jk=f64affe1a0aaca3f",
    "job_url_direct":"https:\/\/hdbj.fa.em2.oraclecloud.com\/hcmUI\/CandidateExperience\/en\/sites\/CX_1\/requisitions\/preview\/26395",
    "title":"Regulatory Affairs Specialist - Energy",
    "company":"Gruppo Hera",
    "location":"Bologna, EMI, IT",
    "date_posted":1774569600000,
    "job_type":null,
    "salary_source":null,
    "interval":null,
    "min_amount":null,
    "max_amount":null,
    "currency":null,
    "is_remote":false,
    "job_level":null,
    "job_function":null,
    "listing_type":null,
    "emails":null,
    "description":"**Il tuo nuovo ruolo**\n\nPer la Funzione **Affari Regolatori e Sistemi Tariffari** di **Hera S.p.A.** , siamo alla ricerca di una figura di **Regulatory Affairs Specialist \\- Energy** da inserire presso la nostra sede di **Bologna.** La figura sarà di supporto al responsabile dell'area nel monitoraggio e nell'analisi delle evoluzioni di policy e di regolazione energetica, valutandone gli impatti sui processi aziendali.\n\n\n**Cosa farai**\n\n* Presidio delle evoluzioni di policy energetica nazionale ed europea e della regolazione del settore attraverso lo studio e l'analisi sistematica delle fonti legislative e regolatorie;\n* Redazione di documenti di sintesi e valutazione, in coordinamento con le strutture di business, circa gli impatti delle opportunità derivanti dal quadro regolatorio e dai nuovi indirizzi di policy;\n* Formulazione e coordinamento del posizionamento di Gruppo rispetto agli orientamenti di ARERA e dei soggetti istituzionali di riferimento, attivando le Funzioni di business impattate e garantendo coerenza nella definizione della linea aziendale;\n* Predisposizione delle risposte ai documenti di consultazione rilevanti per il Gruppo, direttamente o per il tramite delle associazioni di settore;\n* Partecipazione attiva ai gruppi di lavoro delle associazioni di settore e ai focus group promossi da ARERA, rappresentando efficacemente le posizioni delle società del Gruppo;\n* Supporto normativo e regolatorio alle Funzioni di business, sia nella gestione delle richieste di chiarimento e nell'interpretazione degli adempimenti derivanti da nuove disposizioni, sia nella predisposizione di dossier tematici e nella definizione di istanze rappresentate ad ARERA o alle amministrazioni centrali coinvolte;\n* Gestione delle raccolte dati di ARERA, in linea con il livello di servizio concordato con le strutture di business e nel rispetto delle procedure di Gruppo.\n\n**Chi sei**\n\n* Possiedi un titolo di studio in ambito economico, giuridico o ingegneristico;\n* Possiedi una solida conoscenza della regolazione tecnica della distribuzione energia elettrica;\n* Possiedi un solida conoscenza della regolazione tecnica della distribuzione gas;\n* Possiedi una solida conoscenza del processo amministrativo delle autorità indipendenti;\n* Possiedi una solida conoscenza dei processi aziendali core della distribuzione energetica e dei rapporti di filiera.\n\n**Sede**\n\nBOLOGNA, VIALE C. BERTI PICHAT 2\/4\n\n\n**Cosa ti offriamo**\n\n* Inserimento contrattuale permanent;\n* Range di retribuzione annua 45\\.000\\-50\\.000€, in ogni caso commisurata alle competenze e all'esperienza maturata;\n* Pacchetto Welfare aziendale spendibile in un sistema integrato di iniziative e servizi tra cui mobilità sostenibile, iniziative per benessere e la salute individuale e contributi e agevolazioni per la famiglia;\n* Modalità di lavoro ibrida;\n* Accesso alla mensa aziendale \/ ristorante convenzionato;\n* Percorsi di crescita, formazione e sviluppo.\n\n**Chi siamo**\n\nHera S.p.A. è una delle principali multiutility nazionali che opera principalmente nei settori ambientale, idrico ed energetico, ma offre anche servizi per l'illuminazione pubblica e per le telecomunicazioni, adottando sempre un modello di business orientato alla creazione di valore condiviso per tutti gli stakeholder. Quotata nell'indice FTSE MIB della Borsa di Milano dal 2003, nel tempo Hera ha intrapreso un cammino di crescita costante ed equilibrata, incorporando nel Gruppo società attive negli stessi ambiti, ma in territori limitrofi. Oggi si posiziona come 1° operatore nazionale per rifiuti trattati, 2° nel ciclo idrico integrato, 3° nella distribuzione del gas e nella vendita di energia elettrica.\n\n\n**Il nostro impegno verso la diversità e l'inclusione**\n\nDiversità (di genere, cultura, origine) e inclusione sono driver fondamentali per noi che arricchiscono gli ambienti di lavoro, incoraggiano l’innovazione e ci proiettano verso il futuro aiutandoci ad anticipare le sfide del contesto e dei mercati. Le politiche di valorizzazione della diversità sono parte integrante delle strategie d’impresa del Gruppo Hera e sono frutto di un percorso che continua ad arricchirsi nel tempo",
    "company_industry":null,
    "company_url":"https:\/\/it.indeed.com\/cmp\/Gruppo-Hera",
    "company_logo":null,
    "company_url_direct":"https:\/\/www.gruppohera.it",
    "company_addresses":"Bologna",
    "company_num_employees":"5,001 to 10,000",
    "company_revenue":"$5M to $25M (USD)",
    "company_description":null,
    "skills":null,
    "experience_range":null,
    "company_rating":null,
    "company_reviews_count":null,
    "vacancy_count":null,
    "work_from_home_type":null,
    "search_term":"regulatory affairs"
  },
  {
    "id":"li-4389086681",
    "site":"linkedin",
    "job_url":"https:\/\/www.linkedin.com\/jobs\/view\/4389086681",
    "job_url_direct":null,
    "title":"Regulatory Affair Coordinator",
    "company":"Cefla",
    "location":"Imola, Emilia-Romagna, Italy",
    "date_posted":1774224000000,
    "job_type":null,
    "salary_source":null,
    "interval":null,
    "min_amount":null,
    "max_amount":null,
    "currency":null,
    "is_remote":false,
    "job_level":"",
    "job_function":null,
    "listing_type":null,
    "emails":null,
    "description":null,
    "company_industry":null,
    "company_url":"https:\/\/it.linkedin.com\/company\/cefla",
    "company_logo":null,
    "company_url_direct":null,
    "company_addresses":null,
    "company_num_employees":null,
    "company_revenue":null,
    "company_description":null,
    "skills":null,
    "experience_range":null,
    "company_rating":null,
    "company_reviews_count":null,
    "vacancy_count":null,
    "work_from_home_type":null,
    "search_term":"regulatory affairs"
  },
  {
    "id":"in-8d31aafa96ba7fef",
    "site":"indeed",
    "job_url":"https:\/\/it.indeed.com\/viewjob?jk=8d31aafa96ba7fef",
    "job_url_direct":"https:\/\/careers.dentsplysirona.com\/job\/Badia-Polesine-%28RO%29-Automation-Engineer-45021\/1378131233\/?feedId=391933&utm_source=Indeed",
    "title":"Automation Engineer",
    "company":"Dentsply Sirona",
    "location":"Badia Polesine, VEN, IT",
    "date_posted":1774483200000,
    "job_type":null,
    "salary_source":null,
    "interval":null,
    "min_amount":null,
    "max_amount":null,
    "currency":null,
    "is_remote":false,
    "job_level":null,
    "job_function":null,
    "listing_type":null,
    "emails":"careers@dentsplysirona.com",
    "description":"**Requistion ID**: 82740\n\n  \n\nDentsply Sirona is the world’s largest manufacturer of professional dental products and technologies, with a 130\\-year history of innovation and service to the dental industry and patients worldwide. Dentsply Sirona develops, manufactures, and markets a comprehensive solutions offering including dental and oral health products as well as other consumable medical devices under a strong portfolio of world class brands. Dentsply Sirona’s products provide innovative, high\\-quality and effective solutions to advance patient care and deliver better and safer dentistry. Dentsply Sirona’s global headquarters is located in Charlotte, North Carolina, USA. The company’s shares are listed in the United States on NASDAQ under the symbol XRAY.\n\n **Bringing out the best in people**\n\n  \n\n\n\nAs advanced as dentistry is today, we are dedicated to making it even better. Our people have a passion for innovation and are committed to applying it to improve dental care. We live and breathe high performance, working as one global team, bringing out the best in each other for the benefit of dental patients, and the professionals who serve them. If you want to grow and develop as a part of a team that is shaping an industry, then we’re looking for the best to join us.\n\n  \n\n\n\nWorking at Dentsply Sirona you are able to:\n\n  \n\n\n\n**Develop faster** \\- with our commitment to the best professional development.\n\n  \n\n\n\n**Perform better** \\- as part of a high\\-performance, empowering culture.\n\n  \n\n\n\n**Shape an industry** \\- with a market leader that continues to drive innovation.\n\n  \n\n\n\n**Make a difference** \\-by helping improve oral health worldwide.\n\n **For our production site in Badia Polesine, we are looking for an:**\n\n **Automation Engineer**\n\n  \n\nThe position will be responsible for the design, development, and implementation of industrial automation solutions, handling programming, testing, commissioning, process optimization, and technical support to ensure efficiency, quality, and reliability of the systems.\n\n **Responsibilities**\n\n* Responsible for the design and development of automation systems (PLC, HMI, SCADA, robotics), defining process requirements and technical specifications.\n* Responsible for diagnosing complex faults on PLCs, industrial networks, sensors, and actuators.\n* Manages commissioning and testing of systems, organizing Factory Acceptance Tests (FAT) and Site Acceptance Tests (SAT), overseeing start‑up, calibration, and optimization of control logic.\n* Supports the maintenance team in ensuring correct operation and efficiency of systems in compliance with current Safety, Environmental, and Quality procedures.\n* Supports the engineering team with software updates, hardware upgrades, and troubleshooting during start‑ups, restarts, and normal plant operations.\n* Defines process KPIs and performs data analysis to improve efficiency, quality, and scrap reduction (Lean approach).\n* Coordinates suppliers and system integrators during field activities and ensures that all required technical documentation is prepared and archived (diagrams, manuals, declarations of conformity).\n* Supports the QAS (Quality, Environment \\& Safety Manager) in managing interactions with regulatory and certification bodies, and in preparing and reviewing Validation protocols within Operations.\n* Respects company standards, corporate vision, colleagues, and customers.\n\n **Skills**\n\n* Education: Degree in Automation Engineering, Mechatronics, Electronics, or equivalent.\n* Fluent knowledge of Italian and technical English.\n* Experience with MES integration and at least 3 years in a similar role.\n* Knowledge of industry standards and regulations (ISO, CE, Machinery Directive).\n* Technical drawing skills (reading P\\&ID, electrical diagrams, automation layouts).\n* Knowledge of industrial networks (PROFINET, EtherCAT, Ethernet\/IP, Modbus).\n* Industrial robotics experience (Fanuc, Epson, ABB, KUKA, Yaskawa).\n* Knowledge of major SCADA\/HMI systems (WinCC, FactoryTalk, Movicon, Ignition).\n* Basic PLC programming skills (Siemens, Rockwell, Schneider, Omron or others depending on context).\n* Experience with automation system design software (Studio 5000, FactoryTalk).\n* Alignment with company values: Respect (for company standards, vision, colleagues and customers), Responsibility, Collaboration, Reliability, and Agility (continuous improvement).\n* Flexibility: ability to adapt to context and support colleagues and supervisors.\n* Participation in continuous improvement initiatives.\n* Excellent knowledge of Microsoft Office tools.\n* Strong organizational skills, multitasking ability, and autonomy.\n* Precision, proactivity, and punctuality in meeting deadlines.\n\n  \n\nDentsply Sirona is an Equal Opportunity\/ Affirmative Action employer. All qualified applicants will receive consideration for employment without regard to race, color, religion, sex, national origin, age, sexual orientation, disability, or protected Veteran status. We appreciate your interest in Dentsply Sirona.\n\n\nIf you need assistance with completing the online application due to a disability, please send an accommodation request to careers@dentsplysirona.com. Please be sure to include “Accommodation Request” in the subject.",
    "company_industry":null,
    "company_url":"https:\/\/it.indeed.com\/cmp\/Dentsply-Sirona",
    "company_logo":"https:\/\/d2q79iu7y748jz.cloudfront.net\/s\/_squarelogo\/256x256\/b89a6fd178662e93f62c0c0f039b6363",
    "company_url_direct":"https:\/\/www.dentsplysirona.com\/en",
    "company_addresses":null,
    "company_num_employees":"Decline to state",
    "company_revenue":"Decline to state",
    "company_description":"Dentsply Sirona is the world’s largest manufacturer of professional dental products and technologies.",
    "skills":null,
    "experience_range":null,
    "company_rating":null,
    "company_reviews_count":null,
    "vacancy_count":null,
    "work_from_home_type":null,
    "search_term":"regulatory manager"
  },
  {
    "id":"in-4c47336293cea67c",
    "site":"indeed",
    "job_url":"https:\/\/it.indeed.com\/viewjob?jk=4c47336293cea67c",
    "job_url_direct":"https:\/\/jsv3.recruitics.com\/redirect?rx_cid=3436&rx_jobId=R-01225634_1002_rxr-7&rx_url=https%3A%2F%2Fjobs.thermofisher.com%2Fglobal%2Fen%2Fjob%2FR-01225634%2FSenior-CRA%3Frx_a%3D0%26rx_c%3D%26rx_ch%3Djobp4p%26rx_group%3D123525%26rx_id%3D3f9ea852-27f1-11f1-ac06-8f912852c3cc%26rx_job%3DR-01225634_1002_rxr-7%26rx_medium%3Dcpc%26rx_r%3Dnone%26rx_source%3Dindeed%26rx_ts%3D20260330T080427Z%26rx_vp%3Dcpc%26utm_medium%3Dppc%26utm_source%3Drecruitics_indeedorganic",
    "title":"Senior CRA",
    "company":"Thermo Fisher Scientific",
    "location":"Bologna, EMI, IT",
    "date_posted":1774310400000,
    "job_type":"fulltime",
    "salary_source":null,
    "interval":null,
    "min_amount":null,
    "max_amount":null,
    "currency":null,
    "is_remote":true,
    "job_level":null,
    "job_function":null,
    "listing_type":null,
    "emails":null,
    "description":"**Work Schedule**\n\n\nOther**Environmental Conditions**\n\n\nOffice**Job Description**\n\n\nAt PPD, part of Thermo Fisher Scientific, you’ll discover meaningful work that makes a positive impact on a global scale. Join our colleagues in bringing our Mission to life \\- enabling our customers to make the world healthier, cleaner and safer. We provide our teams with the resources needed to achieve individual career goals while taking science a step beyond through research, development and delivery of life\\-changing therapies. With clinical trials conducted in 100\\+ countries and ongoing development of novel frameworks for clinical research through our PPD clinical research portfolio, our work spans laboratory, digital and decentralized clinical trial services. Your determination to deliver quality and accuracy will improve health outcomes that people and communities depend on – now and in the future.\n\n\nThis is a great opportunity for experienced Senior CRA's currently working within the life science sector for pharmaceutical companies, biotech companies or CRO's to work with a world\\-leading CRO across multiple sponsors, various protocols and therapy areas.\n\n\nThese roles can be performed remotely for CRA's based close to our clinical 'hubs': **Milan, Bologna, Florence, Rome** and **Naples.** Travel requirement will be national across Italy.\n\n**Essential Functions:**\n------------------------\n\n* Monitors investigator sites with a risk\\-based monitoring approach: applies root cause analysis (RCA), critical thinking and problem\\-solving skills to identify site processes failure and corrective\/preventive actions to bring the site into compliance and decrease risks.\n* Ensures data accuracy through SDR, SDV and CRF review as applicable through on\\-site and remote monitoring activities.\n* Assess investigational product through physical inventory and records review.\n* Documents observations in reports and letters according to timelines using approved business writing standards.\n* Escalates observed deficiencies and issues to clinical management expeditiously and follows all issues through to resolution. May need to maintain regular contact between monitoring visits with investigative sites to confirm that the protocol is being followed, that previously identified issues are being resolved and that the data is being recorded in a timely manner.\n* Participates in the investigator payment process. Ensures a shared responsibility with other project team members on issues\/findings resolution. Investigates and follows\\-up on findings as applicable.\n* Participates in investigator meetings as necessary. Identifies potential investigators in collaboration with the client company to ensure the acceptability of qualified investigative sites.\n* Initiates clinical trial sites according to the relevant procedures to ensure compliance with the protocol and regulatory and ICH GCP obligations, making recommendations where warranted. Performs trial close out and retrieval of trial materials.\n* Ensures that required essential documents are complete and in place, according to ICH\\-GCP and applicable regulations. Conducts on\\-site file reviews as per project specifications.\n* Provides trial status tracking and progress update reports to the Clinical Team Manager (CTM) as required. Ensures study systems are updated per agreed study conventions (e.g. Clinical Trial Management System).\n* Contributes to the project team by assisting in preparation of project publications\/tools and sharing ideas\/suggestions with team members.\n* Contributes to other project work and initiatives for process improvement, as required.\n\n**Education and Experience:**\n-----------------------------\n\n* University degree in a science related field\n* CRA Qualified as per the Ministerial Decree dated 15\/11\/2011 and **at least 3 years** of independent monitoring experience in clinical development phases II\\-IV\n* Understanding of ICH\\-GCP, EU and FDA requirements\n* Fluency in English and in Italian\n* Valid Driver's License\n\n**Knowledge, Skills and Abilities:**\n------------------------------------\n\n* Proven clinical monitoring skills\n* Demonstrated understanding of medical\/therapeutic area knowledge and medical terminology\n* Demonstrated ability to attain and maintain a working knowledge of ICH GCPs, applicable regulations and procedural documents\n* Well\\-developed critical thinking skills, including but not limited to: critical mindset, in\\-depth investigation for appropriate root cause analysis and problem solving\n* Ability to manage Risk Based Monitoring concepts and processes\n* Good oral and written communication skills, with the ability to communicate effectively with medical personnel\n* Ability to maintain customer focus through the utilization of good listening skills, attention to detail and the ability to perceive customers’ underlying issues\n* Good organizational and time management skills\n* Effective interpersonal skills\n* Attention to detail\n* Ability to remain flexible and adaptable in a wide range of scenarios\n* Ability to work in a team or independently as require\n* Good computer skills: solid knowledge of Microsoft Office and the ability to learn appropriate software\n\n\nAs well as being rewarded a competitive salary, we have an extensive benefits package based around the health and well\\-being of our employees. We have a flexible working culture, where PPD truly value a work\\-life balance. We’ve grown sustainably year on year but continue to offer a collaborative environment, with teams of colleagues eager to share expertise and have fun together. We are a global organization but with a local feel.\n\n**Our 4i Values:**\n\n**Integrity – Innovation – Intensity – Involvement**\n\n\nIf you resonate with our 4i values above, and ultimately wish to accelerate the delivery of safe and effective therapeutics for some of the world’s most urgent health needs, submit your application – we’d love to hear from you!",
    "company_industry":"Industrial Manufacturing",
    "company_url":"https:\/\/it.indeed.com\/cmp\/Thermo-Fisher-Scientific",
    "company_logo":"https:\/\/d2q79iu7y748jz.cloudfront.net\/s\/_squarelogo\/256x256\/65bd2e4bebb79b1432ac3277ffd57ae7",
    "company_url_direct":"https:\/\/www.thermofisher.com\/",
    "company_addresses":"168 Third Avenue, Waltham, MA USA 02451",
    "company_num_employees":"10,000+",
    "company_revenue":"more than $10B (USD)",
    "company_description":"At Thermo Fisher Scientific, our professionals develop critical solutions—and build rewarding careers.",
    "skills":null,
    "experience_range":null,
    "company_rating":null,
    "company_reviews_count":null,
    "vacancy_count":null,
    "work_from_home_type":null,
    "search_term":"regulatory manager"
  },
  {
    "id":"in-6ecc09f74954092c",
    "site":"indeed",
    "job_url":"https:\/\/it.indeed.com\/viewjob?jk=6ecc09f74954092c",
    "job_url_direct":"https:\/\/allegion.wd5.myworkdayjobs.com\/en-US\/careers\/job\/Faenza-Italy---Via-Oberdan\/Senior-Product-Manager---Digital-Solutions_JR35590",
    "title":"Senior Product Manager - Digital Solutions",
    "company":"Allegion",
    "location":"Faenza, EMI, IT",
    "date_posted":1774224000000,
    "job_type":"fulltime",
    "salary_source":null,
    "interval":null,
    "min_amount":null,
    "max_amount":null,
    "currency":null,
    "is_remote":false,
    "job_level":null,
    "job_function":null,
    "listing_type":null,
    "emails":null,
    "description":"**Creating Peace of Mind by Pioneering Safety and Security**\n------------------------------------------------------------\n\n*At Allegion, we help keep the people you know and love safe and secure where they live, work and visit. With more than 30 brands, 12,000\\+ employees globally and products sold in 130 countries, we specialize in security around the doorway and* *beyond. Additionally,* *in 2024 we were awarded the Gallup Exceptional Workplace Award, which recognizes the most engaged workplace cultures in the world.***Key Responsibilities**\nThe Senior Product Manager \\- Digital Solutions will develop and deploy a comprehensive product strategy and roadmap for digital solutions across residential, commercial, and hospitality verticals within the Home and Work division. This role will drive profitable growth by identifying market opportunities, defining product requirements, and leading cross\\-functional teams to deliver innovative digital products that meet customer needs and exceed business objectives.**Specific responsibilities include:*** Product Strategy \\& Vision: Develop and own the end\\-to\\-end product strategy and multi\\-year roadmap for digital solutions spanning residential, commercial, and hospitality markets, ensuring alignment with division goals and market demands.\n* P\\&L Accountability: financial performance of the digital solutions portfolio, including revenue targets, margin optimization, and profitability objectives. Monitor and report on sales and margin performance regularly.\n* Global Collaboration: Build relationships and network with global colleagues to maximize synergies, share best practices, leverage innovation, and utilize product management tools and frameworks.\n* Market Analysis \\& Customer Insights: Analyze market trends, technology advancements, competitor activity, voice of customer (VOC), and regulatory changes across all three verticals to inform strategic product decisions and identify growth opportunities.\n* Product Lifecycle Management: Manage the complete product lifecycle from ideation through development, launch, growth, maturity, and end\\-of\\-life, ensuring products continue to meet evolving customer needs and market dynamics.\n* Innovation \\& Differentiation: Drive innovation initiatives that maintain competitive advantage, establish clear market positioning, and create meaningful points of difference for digital solutions in each vertical.\n* Requirements Definition: Translate customer needs and market opportunities into detailed product requirements, user stories, and technical specifications that guide development teams.\n* Go\\-to\\-Market Strategy: Work closely with sales and marketing leadership to establish pricing strategies, customer segmentation, positioning, branding strategies, and launch programs that maximize profitability and market penetration across different markets.\n* Stakeholder Management: Present product strategies, roadmaps, and performance updates to senior leadership; build consensus and secure resources for strategic initiatives.\n* Voice of Customer Programs: Establish and maintain ongoing VOC programs including customer advisory boards, beta testing, and feedback loops to inform product decisions\n* Thought Leadership: Stay current with emerging technologies, digital transformation trends, IoT platforms, cloud services, and smart building innovations relevant to the residential, commercial, and hospitality sectors\n\n\n\\-\n**Skills and Experience\/Education Requirements****Required Qualifications:*** Bachelor’s degree in business, Engineering, Computer Science, or related field;\n* Minimum 7\\-10 years of product management experience with at least 5 years focused on digital products, software, or connected solutions.\n* Proven track record of successfully launching and scaling digital products in B2B and\/or B2C markets with demonstrable revenue and market share growth.\n* Good technical acumen with ability to understand software architecture, cloud platforms, IoT ecosystems, and emerging technologies.\n* Demonstrated ability to influence senior management and drive strategic decision\\-making through data\\-driven insights.\n* Analytical skills with proficiency in product analytics tools, market research methodologies, and financial modeling.\n* Fluent in English (both written and spoken)\n\n**Preferred Qualifications:*** Experience in hardware\/software integration, smart building technology, access control, or security solutions.\n* Knowledge of residential, commercial real estate, or hospitality industry dynamics and buying behaviors.\n* Understanding of product development processes, supply chain dynamics, and distribution channels in technology or construction industries.\n* Experience working in a matrix organization\n\n**Leadership \\& Communication:*** Effective communication skills (both oral and written) with ability to present complex concepts to diverse audiences.\n\n\n •• Strong leadership skills with ability to drive cross\\-functional teams to deliver on critical business priorities without direct authority.* Strong executive presence and change management capabilities\n* Proven ability to build consensus, manage conflict, and navigate organizational complexity\n* Talent for mentoring and developing junior product managers and cross\\-functional team members\n\n**Business \\& Strategic Skills:*** Strong business acumen with expertise in driving profitable growth through KPIs and financial metrics.\n* Strategic thinking with ability to balance long\\-term vision with short\\-term execution priorities\n* Ability to effectively operate within a matrix environment and collaborate across all levels and functions\n* Customer\\-centric mindset with passion for solving real customer problems.\n\n\nOther Requirements:* Ability to travel as needed (approximately 25\\-30%) to customer sites, trade shows, partner locations, and company facilities.\n* Flexibility to work with global teams across different time zones\n\n**We Celebrate Who We Are!**\n----------------------------\n\n\nAllegion is committed to building and maintaining a diverse and inclusive workplace. Together, we embrace all differences and similarities among colleagues, as well as the differences and similarities within the relationships that we foster with customers, suppliers and the communities where we live and work. Whatever your background, experience, race, color, national origin, religion, age, gender, gender identity, disability status, sexual orientation, protected veteran status, or any other characteristic protected by law, we will make sure that you have every opportunity to impress us in your application and the opportunity to give your best at work, not because we’re required to, but because it’s the right thing to do. We are also committed to providing accommodations for persons with disabilities. If for any reason you cannot apply through our career site and require an accommodation or assistance, please contact our Talent Acquisition Team.\n© Allegion plc, 2023 \\| Block D, Iveagh Court, Harcourt Road, Dublin 2, Co. Dublin, Ireland\nREGISTERED IN IRELAND WITH LIMITED LIABILITY REGISTERED NUMBER 527370\nAllegion is an equal opportunity and affirmative action employer",
    "company_industry":"Consumer Goods And Services",
    "company_url":"https:\/\/it.indeed.com\/cmp\/Allegion",
    "company_logo":null,
    "company_url_direct":"http:\/\/www.allegion.com\/corp\/en\/home\/contact-us.html",
    "company_addresses":"11819 N. Pennsylvania St.\r\nCarmel, IN 46032",
    "company_num_employees":null,
    "company_revenue":null,
    "company_description":"Fun Fact: Schlage, 1 of Allegion’s 23 brands, was invented in 1920 & continues to be an industry leader!",
    "skills":null,
    "experience_range":null,
    "company_rating":null,
    "company_reviews_count":null,
    "vacancy_count":null,
    "work_from_home_type":null,
    "search_term":"regulatory manager"
  },
  {
    "id":"li-4391787180",
    "site":"linkedin",
    "job_url":"https:\/\/www.linkedin.com\/jobs\/view\/4391787180",
    "job_url_direct":null,
    "title":"Quality Assurance",
    "company":"OPOCRIN GROUP",
    "location":"Nonantola, Emilia-Romagna, Italy",
    "date_posted":1774569600000,
    "job_type":null,
    "salary_source":null,
    "interval":null,
    "min_amount":null,
    "max_amount":null,
    "currency":null,
    "is_remote":false,
    "job_level":"",
    "job_function":null,
    "listing_type":null,
    "emails":null,
    "description":null,
    "company_industry":null,
    "company_url":"https:\/\/it.linkedin.com\/company\/opocrin-group",
    "company_logo":null,
    "company_url_direct":null,
    "company_addresses":null,
    "company_num_employees":null,
    "company_revenue":null,
    "company_description":null,
    "skills":null,
    "experience_range":null,
    "company_rating":null,
    "company_reviews_count":null,
    "vacancy_count":null,
    "work_from_home_type":null,
    "search_term":"regulatory specialist"
  },
  {
    "id":"li-4392681381",
    "site":"linkedin",
    "job_url":"https:\/\/www.linkedin.com\/jobs\/view\/4392681381",
    "job_url_direct":null,
    "title":"Customer Quality Assurance  automotive",
    "company":"Adecco",
    "location":"Modena, Emilia-Romagna, Italy",
    "date_posted":1774569600000,
    "job_type":null,
    "salary_source":null,
    "interval":null,
    "min_amount":null,
    "max_amount":null,
    "currency":null,
    "is_remote":false,
    "job_level":"",
    "job_function":null,
    "listing_type":null,
    "emails":null,
    "description":null,
    "company_industry":null,
    "company_url":"https:\/\/ch.linkedin.com\/company\/adecco",
    "company_logo":null,
    "company_url_direct":null,
    "company_addresses":null,
    "company_num_employees":null,
    "company_revenue":null,
    "company_description":null,
    "skills":null,
    "experience_range":null,
    "company_rating":null,
    "company_reviews_count":null,
    "vacancy_count":null,
    "work_from_home_type":null,
    "search_term":"regulatory specialist"
  },
  {
    "id":"li-4391096470",
    "site":"linkedin",
    "job_url":"https:\/\/www.linkedin.com\/jobs\/view\/4391096470",
    "job_url_direct":null,
    "title":"Junior Quality Assurance",
    "company":"SGB Humangest Holding",
    "location":"Medolla, Emilia-Romagna, Italy",
    "date_posted":1774483200000,
    "job_type":null,
    "salary_source":null,
    "interval":null,
    "min_amount":null,
    "max_amount":null,
    "currency":null,
    "is_remote":false,
    "job_level":"",
    "job_function":null,
    "listing_type":null,
    "emails":null,
    "description":null,
    "company_industry":null,
    "company_url":"https:\/\/it.linkedin.com\/company\/humangest-spa",
    "company_logo":null,
    "company_url_direct":null,
    "company_addresses":null,
    "company_num_employees":null,
    "company_revenue":null,
    "company_description":null,
    "skills":null,
    "experience_range":null,
    "company_rating":null,
    "company_reviews_count":null,
    "vacancy_count":null,
    "work_from_home_type":null,
    "search_term":"regulatory specialist"
  },
  {
    "id":"li-4390567716",
    "site":"linkedin",
    "job_url":"https:\/\/www.linkedin.com\/jobs\/view\/4390567716",
    "job_url_direct":null,
    "title":"Customer Quality Assurance",
    "company":"Etjca Group",
    "location":"Modena, Emilia-Romagna, Italy",
    "date_posted":1774483200000,
    "job_type":null,
    "salary_source":null,
    "interval":null,
    "min_amount":null,
    "max_amount":null,
    "currency":null,
    "is_remote":false,
    "job_level":"",
    "job_function":null,
    "listing_type":null,
    "emails":null,
    "description":null,
    "company_industry":null,
    "company_url":"https:\/\/it.linkedin.com\/company\/etjca-group",
    "company_logo":null,
    "company_url_direct":null,
    "company_addresses":null,
    "company_num_employees":null,
    "company_revenue":null,
    "company_description":null,
    "skills":null,
    "experience_range":null,
    "company_rating":null,
    "company_reviews_count":null,
    "vacancy_count":null,
    "work_from_home_type":null,
    "search_term":"regulatory specialist"
  },
  {
    "id":"li-4390352373",
    "site":"linkedin",
    "job_url":"https:\/\/www.linkedin.com\/jobs\/view\/4390352373",
    "job_url_direct":null,
    "title":"Quality Assurance - Tirocinio",
    "company":"Gruppo Montenegro",
    "location":"San Lazzaro di Savena, Emilia-Romagna, Italy",
    "date_posted":1774396800000,
    "job_type":null,
    "salary_source":null,
    "interval":null,
    "min_amount":null,
    "max_amount":null,
    "currency":null,
    "is_remote":false,
    "job_level":"",
    "job_function":null,
    "listing_type":null,
    "emails":null,
    "description":null,
    "company_industry":null,
    "company_url":"https:\/\/it.linkedin.com\/company\/gruppo-montenegro",
    "company_logo":null,
    "company_url_direct":null,
    "company_addresses":null,
    "company_num_employees":null,
    "company_revenue":null,
    "company_description":null,
    "skills":null,
    "experience_range":null,
    "company_rating":null,
    "company_reviews_count":null,
    "vacancy_count":null,
    "work_from_home_type":null,
    "search_term":"regulatory specialist"
  },
  {
    "id":"li-4390010521",
    "site":"linkedin",
    "job_url":"https:\/\/www.linkedin.com\/jobs\/view\/4390010521",
    "job_url_direct":null,
    "title":"Quality Assurance Specialist - Ortofrutta (GlobalGap, Grasp)",
    "company":"Hays",
    "location":"Ferrara, Emilia-Romagna, Italy",
    "date_posted":1774396800000,
    "job_type":null,
    "salary_source":null,
    "interval":null,
    "min_amount":null,
    "max_amount":null,
    "currency":null,
    "is_remote":false,
    "job_level":"",
    "job_function":null,
    "listing_type":null,
    "emails":null,
    "description":null,
    "company_industry":null,
    "company_url":"https:\/\/uk.linkedin.com\/company\/hays",
    "company_logo":null,
    "company_url_direct":null,
    "company_addresses":null,
    "company_num_employees":null,
    "company_revenue":null,
    "company_description":null,
    "skills":null,
    "experience_range":null,
    "company_rating":null,
    "company_reviews_count":null,
    "vacancy_count":null,
    "work_from_home_type":null,
    "search_term":"regulatory specialist"
  },
  {
    "id":"in-be53a0c3fe8753d1",
    "site":"indeed",
    "job_url":"https:\/\/it.indeed.com\/viewjob?jk=be53a0c3fe8753d1",
    "job_url_direct":"https:\/\/careers.geotab.com\/jobs\/description\/5150492008\/",
    "title":"Field Services Coordinator (12 Month Contract)",
    "company":"Geotab",
    "location":"Ferrara, EMI, IT",
    "date_posted":1774483200000,
    "job_type":null,
    "salary_source":null,
    "interval":null,
    "min_amount":null,
    "max_amount":null,
    "currency":null,
    "is_remote":true,
    "job_level":null,
    "job_function":null,
    "listing_type":null,
    "emails":"careers@geotab.com",
    "description":"Basis:\n\n\nFixed Term Employee\n\n\nArea of Interest:\n\n\nSupport Operations\n\n\nLocation:\n\n\nFerrara, Italy\n\n\n**Who we are:**\n---------------\n\n\nGeotab ® is a global leader in IoT and connected transportation and certified “Great Place to Work™.” We are a company of diverse and talented individuals who work together to help businesses grow and succeed, and increase the safety and sustainability of our communities.\n\nGeotab is advancing security, connecting commercial vehicles to the internet and providing web\\-based analytics to help customers better manage their fleets. Geotab’s open platform and Geotab Marketplace ®, offering hundreds of third\\-party solution options, allows both small and large businesses to automate operations by integrating vehicle data with their other data assets. Processing billions of data points a day, Geotab leverages data analytics and machine learning to improve productivity, optimize fleets through the reduction of fuel consumption, enhance driver safety and achieve strong compliance to regulatory changes.\n\nOur team is growing and we’re looking for people who follow their passion, think differently and want to make an impact. Ours is a fast paced, ever changing environment. Geotabbers accept that challenge and are willing to take on new tasks and activities \\- ones that may not always be described in the initial job description. Join us for a fulfilling career with opportunities to innovate, great benefits, and our fun and inclusive work culture. Reach your full potential with Geotab. To see what it’s like to be a Geotabber, check out our blog and follow us @InsideGeotab on Instagram. Join our talent network to learn more about job opportunities and company news.\n**Who you are:**\n----------------\n\n\n\nWe are always looking for amazing talent who can contribute to our growth and deliver results! Geotab is seeking a Field Services Coordinator who will support operations across multiple European markets. If you love technology and are keen to join an industry leader — we would love to hear from you!\n\n  \n\n**What you'll do:**\n-------------------\n\n\n\nAs a Field Services Coordinator, your key area of responsibility will be managing complex service operations across borders and cultures. You will need to work closely with field technicians, customers, and internal teams like Logistics, Sales, and Customer Success, as well as communicate with third\\-party service partners.  \n\nTo be successful in this role, you will be a highly organized professional with strong technical knowledge and the ability to manage multiple timelines to ensure timely results. In addition, the successful candidate will have strong analytical skills with an ability to identify process improvements, increase efficiency, and ensure compliance with local regulations and safety standards.\n\n  \n\n**How you'll make an impact:**\n------------------------------\n\n\n* Coordinate and schedule field service activities (installations, maintenance, rip and replace) across assigned market(s).\n* Act as the primary point of contact between field technicians, customers, and internal teams.\n* Manage service requests, work orders, and ensure timely completion of field operations.\n* Track and report on service KPIs, SLAs, and field performance metrics.\n* Maintain accurate records in internal systems.\n* Collaborate with other teams (logistics, sales, training, customer success) to ensure a smooth and successful customer experience.\n* Support coordination of third\\-party service partners and subcontractors.\n* Identify process improvements to increase field service efficiency and customer satisfaction.\n* Escalate technical issues to engineering or product teams as needed.\n* Ensure compliance with local regulations, health \\& safety standards, and company policies.\n\n**What you'll bring to this role:**\n-----------------------------------\n\n\n* Exceptional verbal and written fluency in English and Italian is required, with professional level proficiency in French preferred.\n* 2\\+ years of experience in field service coordination, logistics, operations, or a related technical coordination role.\n* Experience in telematics, fleet management, automotive, IoT, or a related technology sector is a strong asset.\n* Post\\-secondary education in a technical, logistics, or business\\-related field (or equivalent experience)\n* Familiarity with vehicle electrical systems and hardware installation processes.\n* Ability to read and interpret technical documentation and installation guides.\n* Proficiency with service management platforms.\n* Comfortable using data and reporting tools to track service performance.\n* Comfortable integrating AI usage in the daily duties.\n* Exceptional organizational and time management skills — ability to manage multiple priorities across different markets and time zones.\n* Strong communication skills — able to coordinate effectively with diverse, cross\\-functional, and multicultural teams.\n* Detail\\-oriented with a proactive, solution\\-driven mindset.\n* Ability to work autonomously in a fast\\-paced, remote environment.\n* Customer\\-centric approach with a strong sense of accountability.\n* This position is location\\-flexible within Europe. Candidates will not necessarily be based in the country they support.\nIf you got this far, we hope you're feeling excited about this role! Even if you don't feel you meet every single requirement, we still encourage you to apply.\n\n**Please note: Geotab does not accept agency resumes and is not responsible for any fees related to unsolicited resumes. Please do not forward resumes to Geotab employees.**\n\n**How we work:**\n----------------\n\n\nAt Geotab, we have adopted a flexible hybrid working model in that we have systems, functions, programs and policies in place to support both in\\-person and virtual work. However, you are welcomed and encouraged to come into our beautiful, safe, clean offices as often as you like. When working from home, you are required to have a reliable internet connection with at least 50mb DL\/10mb UL. Virtual work is supported with cloud\\-based applications, collaboration tools and asynchronous working. The health and safety of employees are a top priority. We encourage work\\-life balance and keep the Geotab culture going strong with online social events, chat rooms and gatherings. Join us and help reshape the future of technology!\n\nWe believe that ensuring diversity is fundamental to our future growth and progress and is an integral part of our business. We believe that success happens where new ideas can flourish – in an environment that is rich in diversity and a place where people from various backgrounds can work together. Geotab encourages applications from all qualified individuals. We are committed to accommodating people with disabilities during the recruitment and assessment processes and when people are hired. We will ensure the accessibility needs of employees with disabilities are taken into account as part of performance management, career development, training and redeployment processes. If you require accommodation at any stage of the application process or want more information about our diversity and inclusion as well as accommodation policies and practices, please contact us at careers@geotab.com. By submitting a job application to Geotab Inc. or its affiliates and subsidiaries (collectively, “Geotab”), you acknowledge Geotab’s collection, use and disclosure of your personal data in accordance with our Privacy Policy.",
    "company_industry":"Internet And Software",
    "company_url":"https:\/\/it.indeed.com\/cmp\/Geotab",
    "company_logo":"https:\/\/d2q79iu7y748jz.cloudfront.net\/s\/_squarelogo\/256x256\/cf4cbc18f93ff43b6edcf93b604257ef",
    "company_url_direct":"https:\/\/careers.geotab.com\/",
    "company_addresses":"2440 Winston Park Drive\r\nOakville, Ontario\r\nCanada\r\nL6H 7V2",
    "company_num_employees":"1,001 to 5,000",
    "company_revenue":"$100M to $500M (USD)",
    "company_description":"We are the #1 commercial telematics company in the world with almost 3 million subscribers and 40 billion data points processed every day. Learn more about telematics and our solutions at geotab.com.",
    "skills":null,
    "experience_range":null,
    "company_rating":null,
    "company_reviews_count":null,
    "vacancy_count":null,
    "work_from_home_type":null,
    "search_term":"qualified person"
  },
  {
    "id":"in-9904c5e7bb528e96",
    "site":"indeed",
    "job_url":"https:\/\/it.indeed.com\/viewjob?jk=9904c5e7bb528e96",
    "job_url_direct":"https:\/\/careers.dentsplysirona.com\/job\/Badia-Polesine-%28RO%29-QA-Supervisor-45021\/1378403333\/?feedId=391933&utm_source=Indeed",
    "title":"QA Supervisor",
    "company":"Dentsply Sirona",
    "location":"Badia Polesine, VEN, IT",
    "date_posted":1774569600000,
    "job_type":null,
    "salary_source":null,
    "interval":null,
    "min_amount":null,
    "max_amount":null,
    "currency":null,
    "is_remote":false,
    "job_level":null,
    "job_function":null,
    "listing_type":null,
    "emails":"careers@dentsplysirona.com",
    "description":"**Requistion ID**: 82736\n\n  \n\nDENTSPLY SIRONA è il più grande produttore mondiale di prodotti dentali professionali e di tecnologie, con una storia di 130 anni di innovazione e servizi per il settore dentale e per i pazienti in tutto il mondo. DENTSPLY SIRONA sviluppa, produce e commercializza un’ampia offerta di soluzioni complete, come anche prodotti per la salute orale e dentale, nonché altri dispositivi medici utilizzati nell'ambito di un vasto portafoglio di marchi di fama mondiale. Come Dental Solution Company TM, i prodotti di Dentsply Sirona forniscono soluzioni efficaci, innovative e di alta qualità per migliorare la cura del paziente e fornire un servizio di odontoiatria sempre migliore, più sicuro e più veloce. La sede globale di Dentsply Sirona si trova a Charlotte, North Carolina. Le azioni della società sono pubblicate al NASDAQ, negli Stati Uniti con il simbolo XRAY.\n\n **Trarre il meglio dalle persone**\n\n  \n\nPer quanto avanzata sia oggi l'odontoiatria, ci dedichiamo a renderla ancora migliore. Le nostre persone hanno una passione per l'innovazione e si impegnano ad applicarla per migliorare le cure dentali. Viviamo e respiriamo elevate prestazioni, lavorando come un unico team globale, facendo emergere il meglio l'uno nell'altro a beneficio dei pazienti e dei professionisti del dentale che li servono. Se vuoi crescere e sviluppare come parte di un team che sta plasmando un settore, allora stiamo cercando il meglio per unirsi a noi.\n\n  \n\nLavorando presso Dentsply Sirona è possibile:\n\n **Cresci più velocemente**...il nostro impegno per un migliore sviluppo professionale.\n\n **Lavora meglio**...nell'ambito di una cultura aziendale basata su elevate prestazioni e consapevolezza.\n\n **Dai forma al settore**...con un leader di mercato che continua a guidare l'innovazione.\n\n **Fai la differenza**...aiutando il miglioramento della salute orale nel mondo.\n\n  \n\nPer il nostro sito produttivo di Badia Polesine ricerchiamo un\/una:\n\n **QA Supervisor**\n\n  \n\nLa figura, rispondendo al Sr. QA Manager, dovrà garantire che le attività di ispezione sui materiali (in accettazione, in process e sul prodotto finito) vengano condotte in accordo ai requisiti stabiliti.\n\n **Responsabilità:**\n\n* Garantire i processi di audit interno, calibrazione, investigazione dei reclami ed investigazione sulle non conformità e CAPA siano eseguite in accordo agli standard aziendali\n* Garantire che il personale di qualità sia correttamente formato ed informato sulle procedure applicabili.\n* Conoscenza della norma ISO 13485, MDR ed altre correlate al mondo dei dispositivi medici\n* Capacità di bilanciare le responsabilità individuali e quelle del team e contribuire ad un ambiente di lavoro positivo\n* Familiarità con i piani di campionamento (ANSI, AQL ecc.)\n* Qualifica come Auditor interno\n* Conoscenza delle buone pratiche di laboratorio\n\n **Competenze:**\n\n* Esperienza in materia di controllo qualità nei dispositivi medici o in settori simili\n* Conoscenza del pacchetto Microsoft Office\n* Preferibile saper interpretare disegni meccanici\n* Conoscenza base dell’uso di calibratori, microscopi, bilance digitali, comparatori ottici\n* Conoscenza del funzionamento di ERP (SAP\/AX)\n* Predisposizione al lavoro di squadra\n* Buona capacità comunicativa sia scritta che orale\n* Conoscenza fluente della lingua italiana.\n* Conoscenza lingua inglese. E’ sufficiente un livello B2\n* Ordine e precisione nella registrazione dei dati e nella loro corretta archiviazione\n* Adesione ai valori aziendali di Rispetto (degli standard aziendali, della visione aziendale, dei colleghi e dei clienti), Responsabilità, Collaborazione, Affidabilità e Agilità (miglioramento continuo).\n\n  \n\n\\#LI\\-IC1\n\n  \n\nDentsply Sirona è un’Azienda di Pari Opportunità \/ Azione Positiva. Ogni candidato qualificato verrà valutato senza distinzione di razza, colore, religione, sesso, nazionalità, età, orientamento sessuale, disabilità. Apprezziamo il tuo interesse per Dentsply Sirona. Se hai bisogno di assistenza per completare la domanda on\\-line a causa di una disabilità, ti preghiamo di inviare una richiesta di supporto per la compilazione a: careers@dentsplysirona.com. Ti chiediamo di essere sicuro\/a di aver indicato nell’oggetto \"Richiesta di supporto\".",
    "company_industry":null,
    "company_url":"https:\/\/it.indeed.com\/cmp\/Dentsply-Sirona",
    "company_logo":"https:\/\/d2q79iu7y748jz.cloudfront.net\/s\/_squarelogo\/256x256\/b89a6fd178662e93f62c0c0f039b6363",
    "company_url_direct":"https:\/\/www.dentsplysirona.com\/en",
    "company_addresses":null,
    "company_num_employees":"Decline to state",
    "company_revenue":"Decline to state",
    "company_description":"Dentsply Sirona is the world’s largest manufacturer of professional dental products and technologies.",
    "skills":null,
    "experience_range":null,
    "company_rating":null,
    "company_reviews_count":null,
    "vacancy_count":null,
    "work_from_home_type":null,
    "search_term":"persona qualificata"
  },
  {
    "id":"in-c709f4ffb5f063d6",
    "site":"indeed",
    "job_url":"https:\/\/it.indeed.com\/viewjob?jk=c709f4ffb5f063d6",
    "job_url_direct":"https:\/\/careers.dentsplysirona.com\/job\/Badia-Polesine-%28RO%29-HSE-Specialist-45021\/1377877833\/?feedId=391933&utm_source=Indeed",
    "title":"HSE Specialist",
    "company":"Dentsply Sirona",
    "location":"Badia Polesine, VEN, IT",
    "date_posted":1774483200000,
    "job_type":null,
    "salary_source":null,
    "interval":null,
    "min_amount":null,
    "max_amount":null,
    "currency":null,
    "is_remote":false,
    "job_level":null,
    "job_function":null,
    "listing_type":null,
    "emails":"careers@dentsplysirona.com",
    "description":"DENTSPLY SIRONA è il più grande produttore mondiale di prodotti dentali professionali e di tecnologie, con una storia di 130 anni di innovazione e servizi per il settore dentale e per i pazienti in tutto il mondo. DENTSPLY SIRONA sviluppa, produce e commercializza un’ampia offerta di soluzioni complete, come anche prodotti per la salute orale e dentale, nonché altri dispositivi medici utilizzati nell'ambito di un vasto portafoglio di marchi di fama mondiale. Come Dental Solution Company TM, i prodotti di Dentsply Sirona forniscono soluzioni efficaci, innovative e di alta qualità per migliorare la cura del paziente e fornire un servizio di odontoiatria sempre migliore, più sicuro e più veloce. La sede globale di Dentsply Sirona si trova a Charlotte, North Carolina. Le azioni della società sono pubblicate al NASDAQ, negli Stati Uniti con il simbolo XRAY.\n\n **Trarre il meglio dalle persone**\n\n  \n\nPer quanto avanzata sia oggi l'odontoiatria, ci dedichiamo a renderla ancora migliore. Le nostre persone hanno una passione per l'innovazione e si impegnano ad applicarla per migliorare le cure dentali. Viviamo e respiriamo elevate prestazioni, lavorando come un unico team globale, facendo emergere il meglio l'uno nell'altro a beneficio dei pazienti e dei professionisti del dentale che li servono. Se vuoi crescere e sviluppare come parte di un team che sta plasmando un settore, allora stiamo cercando il meglio per unirsi a noi.\n\n  \n\nLavorando presso Dentsply Sirona è possibile:\n\n **Cresci più velocemente**...il nostro impegno per un migliore sviluppo professionale.\n\n **Lavora meglio**...nell'ambito di una cultura aziendale basata su elevate prestazioni e consapevolezza.\n\n **Dai forma al settore**...con un leader di mercato che continua a guidare l'innovazione.\n\n **Fai la differenza**...aiutando il miglioramento della salute orale nel mondo.\n\n  \n\nPer il nostro sito produttivo di Badia Polesine ricerchiamo un\/una:\n\n **HSE Specialist**\n\n  \n\n\n\nLa figura supporta a diretto riporto dell’HSE Manager avrà le seguenti responsabilità.\n\n **Responsabilità:**\n\n* Sulla base del piano annuale dei controlli di Salute e Sicurezza sul Lavoro assicura l'esecuzione dei controlli per il mantenimento dello stato di sicurezza degli impianti, attrezzature e luoghi di lavoro in tutte le aree aziendali garantendo interventi tempestivi ed efficaci.\n* E’ responsabile della ottemperanza aziendale alla direttiva PED.\n* E’ responsabile della organizzazione della formazione di sicurezza del personale aziendale gestendo sia l’inserimento dei nuovi assunti che gli aggiornamenti degli attuali dipendenti.\n* E’ responsabile della compilazione delle indagini sugli infortuni o mancati infortuni individuando le opportune azioni correttive. Mantiene aggiornato il database per il calcolo degli indici sugli infortuni e mancati infortuni e indici di gravità.\n* Gestisce la documentazione relativa all’art.26 del D.lgs 81 e promuove la coordinazione e il coordinamento con le ditte esterne\n* Mantiene i rapporti con il Medico Competente e collabora con esso per la pianificazione e l’effettuazione del sopralluogo in ambiente di lavoro e per il successivo aggiornamento del Protocollo Sanitario se necessario.\n* Collabora con il team per la gestione del Sistema Gestione Sicurezza ed il rinnovo delle certificazioni quali ISO 45001 ed ISO 14001\\.\n* Promozione di campagne di sensibilizzazione del personale in materia HSE.\n* Supporto attivo ai vari Reparti operativi circa la redazione di procedure di sicurezza.\n* Supporto nella Redazione, Gestione e Aggiornamento del Documento di Valutazione dei Rischi\n* Promozione, organizzazione e conduzione di incontri di formazione e\/o informazione per il personale\n* Verifica costante del rispetto delle disposizioni di legge in materia HSE per tutte le attività svolte all'interno dello Stabilimento\n* Partecipazione alle iniziative di miglioramento continuo\n\n**Competenze**\n\n* Istruzione universitaria o post\\-universitaria attinente alla materia salute e sicurezza\n* Conoscenza fluente della lingua italiana.\n* Lingua Inglese fluente\/upper intermediate (B2\\);\n* Buona\/ottima conoscenza di Microsoft Office;\n* Capacità di auto organizzazione e gestione progetti (time planning, milestones)\n* Gradita precedente esperienza di lavoro in aziende industriali\n* Adesione ai valori aziendali di Rispetto (degli standard aziendali, della visione aziendale, dei colleghi e dei clienti, dei processi e delle istruzioni operative), Responsabilità, Collaborazione, Affidabilità e Agilità (miglioramento continuo)\n* Precisione e attenzione, capacità di analisi ed elaborazione di documenti e regolamenti\n* Flessibilità: adattare il proprio operato al contesto, essere disponibili con colleghi e responsabili\n* Collaborazione e teamwork con i colleghi e responsabili del proprio e di altri reparti\n\n\n\\#LI\\-IC1\n\n  \n\nDentsply Sirona è un’Azienda di Pari Opportunità \/ Azione Positiva. Ogni candidato qualificato verrà valutato senza distinzione di razza, colore, religione, sesso, nazionalità, età, orientamento sessuale, disabilità. Apprezziamo il tuo interesse per Dentsply Sirona. Se hai bisogno di assistenza per completare la domanda on\\-line a causa di una disabilità, ti preghiamo di inviare una richiesta di supporto per la compilazione a: careers@dentsplysirona.com. Ti chiediamo di essere sicuro\/a di aver indicato nell’oggetto \"Richiesta di supporto\".",
    "company_industry":null,
    "company_url":"https:\/\/it.indeed.com\/cmp\/Dentsply-Sirona",
    "company_logo":"https:\/\/d2q79iu7y748jz.cloudfront.net\/s\/_squarelogo\/256x256\/b89a6fd178662e93f62c0c0f039b6363",
    "company_url_direct":"https:\/\/www.dentsplysirona.com\/en",
    "company_addresses":null,
    "company_num_employees":"Decline to state",
    "company_revenue":"Decline to state",
    "company_description":"Dentsply Sirona is the world’s largest manufacturer of professional dental products and technologies.",
    "skills":null,
    "experience_range":null,
    "company_rating":null,
    "company_reviews_count":null,
    "vacancy_count":null,
    "work_from_home_type":null,
    "search_term":"persona qualificata"
  },
  {
    "id":"in-eeb924c7476d4a15",
    "site":"indeed",
    "job_url":"https:\/\/it.indeed.com\/viewjob?jk=eeb924c7476d4a15",
    "job_url_direct":"http:\/\/it.indeed.com\/job\/operatore-gruppi-elettrogeni-eeb924c7476d4a15",
    "title":"Operatore Gruppi Elettrogeni",
    "company":"Powering srl",
    "location":"Modena, EMI, IT",
    "date_posted":1774396800000,
    "job_type":"fulltime",
    "salary_source":null,
    "interval":null,
    "min_amount":null,
    "max_amount":null,
    "currency":null,
    "is_remote":true,
    "job_level":null,
    "job_function":null,
    "listing_type":null,
    "emails":null,
    "description":"**Chi siamo**\n\nPowering è una realtà leader in Italia nel settore del noleggio e della gestione di gruppi elettrogeni. L’azienda si distingue per la sua presenza capillare sul territorio nazionale, grazie a oltre 60 centri logistici distribuiti in tutta Italia, che garantiscono interventi tempestivi anche nelle aree più remote. La nostra Centrale Operativa attiva 24 ore su 24, 7 giorni su 7, assicura un servizio continuo e altamente reattivo, in grado di rispondere a qualsiasi esigenza energetica, programmata o d’emergenza, con rapidità ed efficienza. Con una flotta in continua evoluzione e personale altamente qualificato, Powering è sinonimo di affidabilità, innovazione e servizio al cliente.\n\n**Descrizione del ruolo**\n\nSiamo alla ricerca di un **Tecnico Addetto al Rifornimento e Manutenzione Gruppi Elettrogeni** motivato e con competenze meccaniche, da inserire nel nostro team operativo.\n\n**Responsabilità principali:**\n\nLa risorsa selezionata si occuperà delle seguenti attività:\n\n* Effettuare il rifornimento di carburante dei gruppi elettrogeni presso i siti dei clienti\n* Eseguire controlli periodici e manutenzione ordinaria dei gruppi elettrogeni\n* Verificare il corretto funzionamento degli impianti attraverso test e ispezioni visive\n* Diagnosticare e risolvere problematiche meccaniche di base\n* Compilare report tecnici relativi agli interventi effettuati\n* Gestire le scorte di materiali di consumo e ricambi necessari\n* Garantire il rispetto delle normative di sicurezza durante tutte le operazioni\n* Mantenere rapporti professionali con i clienti durante gli interventi in loco\n\n**Requisiti**\n\nCompetenze Tecniche:\n\n* Conoscenze meccaniche di base o esperienza pregressa in ambito meccanico\n* Capacità di lettura e interpretazione di schemi tecnici (preferibile)\n* Familiarità con strumenti e attrezzature meccaniche\n* Disponibilità a effettuare trasferte anche di più giorni\n\nFormazione:\n\n* Diploma di scuola secondaria superiore, preferibilmente in ambito tecnico\\-meccanico\n\nCompetenze Personali:\n\n* Autonomia operativa e capacità di problem solving\n* Attitudine al lavoro sul campo e disponibilità a trasferte\n* Precisione e attenzione ai dettagli\n* Buone capacità organizzative\n* Orientamento alla sicurezza sul lavoro\n* **Patente C\\+CQC in corso di validità (indispensabile)**\n\nRequisiti Preferenziali:\n\n* Esperienza pregressa nella manutenzione di gruppi elettrogeni o motori diesel\n* Conoscenze di base di elettrotecnica\n* Attestati di sicurezza per lavori in quota o in ambienti confinati\n\n**Cosa Offriamo:**\n\n· Formazione tecnica specifica sui nostri impianti\n\n· Dotazione di strumenti di lavoro e dispositivi di protezione individuale\n\n· Ambiente di lavoro dinamico e in crescita\n\n· Possibilità di sviluppo professionale\n\n*“In Powering crediamo che la diversità sia un valore. Favoriamo un ambiente di lavoro inclusivo e incoraggiamo la candidatura di persone appartenenti a minoranze e categorie protette, nel rispetto delle pari opportunità.”*\n\nContratto di lavoro: Tempo pieno, Somministrazione\n\nBenefit:\n\n* Buoni pasto\n* Cellulare aziendale\n* Supporto allo sviluppo professionale\n\nEsperienza:\n\n* Autista: 5 anni (Obbligatorio)\n\nAbilitazione\/Certificazione:\n\n* Patente C (Obbligatorio)\n* Patente CQC (Obbligatorio)\n* Patente CE (Preferenziale)\n\nSede di lavoro: Di persona",
    "company_industry":null,
    "company_url":"https:\/\/it.indeed.com\/cmp\/Powering-Srl-1",
    "company_logo":null,
    "company_url_direct":null,
    "company_addresses":null,
    "company_num_employees":null,
    "company_revenue":null,
    "company_description":null,
    "skills":null,
    "experience_range":null,
    "company_rating":null,
    "company_reviews_count":null,
    "vacancy_count":null,
    "work_from_home_type":null,
    "search_term":"persona qualificata"
  },
  {
    "id":"in-3a1514cb4f54fe6e",
    "site":"indeed",
    "job_url":"https:\/\/it.indeed.com\/viewjob?jk=3a1514cb4f54fe6e",
    "job_url_direct":"http:\/\/it.indeed.com\/job\/commerciale-outbound-lead-generation-b2b-marketing-digital-3a1514cb4f54fe6e",
    "title":"Commerciale Outbound (Lead Generation B2B) – Marketing & Digital",
    "company":"Lynx 2000",
    "location":"Modena, EMI, IT",
    "date_posted":1774310400000,
    "job_type":null,
    "salary_source":null,
    "interval":null,
    "min_amount":null,
    "max_amount":null,
    "currency":null,
    "is_remote":false,
    "job_level":null,
    "job_function":null,
    "listing_type":null,
    "emails":null,
    "description":"**Chi siamo**\n\nSiamo Lynx, agenzia di marketing che lavora con aziende B2B su crescita, lead generation e posizionamento digitale.\n\n**Stiamo espandendo il team commerciale con una figura outbound che ci aiuti a generare nuove opportunità in modo strutturato.**\n\nStiamo cercando qualcuno che voglia costruire risultati (e guadagni reali)\n\n**Ammettiamo che non è un lavoro per tutti**\n\n**Questo ruolo è adatto a te se:**\n\n* non hai paura di prendere il telefono\n* sai gestire il rifiuto senza perderti\n* hai voglia di guadagnare più della media\n\n**Se cerchi comfort, routine o “posto tranquillo”, probabilmente non è il contesto giusto.**\n\n**Quale sarà il tuo lavoro**\n\n* Contatterai aziende target (telefono \\+ LinkedIn)\n* Genererai appuntamenti qualificati per il team commerciale\n* Lavorerai su liste profilate (nessuna chiamata random)\n* Utilizzerai campagne e servizi con domanda reale\n\n**La persona che stiamo cercando ha**\n\n* Mentalità commerciale e orientamento ai risultati\n* Esperienza (anche minima) in telemarketing o vendita\n* Costanza e disciplina\n* Fame di crescita economica\n\n**Nota importante: qui vieni premiato per quello che produci, non per il tempo che passi seduto**\n\n**Abbiamo strutturato per te un piano compensi, eccolo:**\n\n* Fisso mensile: 1000€\n* Gettone bonus per ogni appuntamento in target fissato\n* % sulle vendite generate dai commerciali sugli appuntamenti da te fissati\n* Bonus al raggiungimento di obiettivi mensili\n\n**Ovviamente non esiste un tetto massimo a quanto puoi guadagnare**\n\n**Ti starai chiedendo perché Lynx?**\n\n* Metodo commerciale già testato e funzionante\n* Lavori su target e servizi richiesti dal mercato\n* Formazione concreta e operativa\n* Ambiente diretto, meritocratico e orientato ai risultati\n* Possibilità reale di crescita\n\n**Modalità di collaborazione:**\n\n**Collaborazione in partita IVA, con gestione autonoma dell’attività.**\n\nContratto di lavoro: Contratto con partita IVA\n\nRetribuzione: €1\\.000,00 \\- €10\\.000,00 al mese\n\nSede di lavoro: Ibrido\/da remoto (41126 Modena)",
    "company_industry":null,
    "company_url":"https:\/\/it.indeed.com\/cmp\/Lynx-2000",
    "company_logo":"https:\/\/d2q79iu7y748jz.cloudfront.net\/s\/_squarelogo\/256x256\/cfecd1f0eb46d507851e52e32713c052",
    "company_url_direct":"http:\/\/www.lynx2000.it",
    "company_addresses":"Strada Scaglia Est 15, 41126 Modena",
    "company_num_employees":"11 to 50",
    "company_revenue":null,
    "company_description":null,
    "skills":null,
    "experience_range":null,
    "company_rating":null,
    "company_reviews_count":null,
    "vacancy_count":null,
    "work_from_home_type":null,
    "search_term":"persona qualificata"
  },
  {
    "id":"in-e181d75db41005aa",
    "site":"indeed",
    "job_url":"https:\/\/it.indeed.com\/viewjob?jk=e181d75db41005aa",
    "job_url_direct":"https:\/\/salesvalley.teamtailor.com\/jobs\/7026691-commerciale-fotovoltaico-bologna-romagna",
    "title":"Commerciale Fotovoltaico – Bologna & Romagna",
    "company":"SalesValley",
    "location":"Bologna, EMI, IT",
    "date_posted":1767916800000,
    "job_type":null,
    "salary_source":null,
    "interval":null,
    "min_amount":null,
    "max_amount":null,
    "currency":null,
    "is_remote":false,
    "job_level":null,
    "job_function":null,
    "listing_type":null,
    "emails":null,
    "description":"**Sales Valley** è una boutique HR specializzata nella selezione di profili commerciali.  \n\nPer un’azienda italiana in rapida crescita nel settore delle **energie rinnovabili** e dell’**efficienza energetica** (impianti fotovoltaici, solare termico, infissi ad alta prestazione), selezioniamo un Commerciale per la zona di Bologna e Romagna.  \n\nLa realtà cliente, con sede a Parma e studio tecnico a Treviso, conta oltre **50 risorse tra team interno e rete vendita**.  \n\nCollabora con **grandi gruppi industriali e utility nazionali** – tra cui **Barilla, IREN ed EDISON** – e si distingue per **qualità tecnica, visione sostenibile e approccio consulenziale**.  \n\nCerchiamo un Commerciale Fotovoltaico con esperienza nella vendita sul campo, interessat a crescere in un settore in forte espansione come quello delle energie rinnovabili.  \n\nUn’opportunità concreta per entrare in una realtà solida, con **lead qualificati mensili**, **formazione continua** e **possibilità di sviluppare il proprio mercato in autonomia**.\n\n**Area di competenza**\n\n\nZona di lavoro: **Bologna, Romagna**, con possibilità di espansione in **Veneto e Marche** (entro 100 km dalla residenza).\n\n**Cosa farai**\n\n* **Gestirai trattative di vendita B2C** nel settore fotovoltaico e delle soluzioni energetiche per privati.\n* **Acquisirai nuovi clienti** attraverso attività sul campo e canali digitali, con **lead qualificati forniti dall’azienda**.\n* **Parteciperai a fiere ed eventi di settore**, promuovendo soluzioni sostenibili.\n* **Utilizzerai strumenti digitali** (CRM, LinkedIn) per la generazione di contatti.\n* **Svilupperai il canale B2B**, gestendo trattative con aziende e clienti industriali.\n\n**Chi cerchiamo**\n\n\nUn professionista della vendita con mentalità imprenditoriale, capace di lavorare in autonomia e orientat al risultato.\n\n**Requisiti obbligatori**\n\n* **Esperienza commerciale sul campo**, preferibilmente nei settori energia, impiantistica o affini.\n* **Capacità di lavorare per obiettivi**, gestendo in autonomia il proprio territorio.\n* **Ottime doti relazionali e comunicative**, sia con privati che con aziende.\n* Possesso di **auto, PC e telefono personali**.\n* Iscrizione **Enasarco** o **disponibilità a iscriversi.**\n\n***Requisiti preferenziali***\n\n* *Esperienza nella vendita di impianti fotovoltaici o soluzioni per l’efficienza energetica.*\n* *Familiarità con trattative complesse e utilizzo di* ***strumenti digitali per la vendita****.*\n\n**Cosa offriamo**\n\n* **Collaborazione con Partita IVA (agente commerciale)**.\n* **Fisso mensile garantito**, in base all’esperienza.\n* **Provvigioni su vendite B2C e B2B**, con un sistema di incentivazione strutturato e premi mensili legati a performance e referenze.\n* **Bonus on top fino a 2\\.500 € al mese** e **premi annuali** basati sui risultati.\n* **Lead qualificati mensili forniti dall’azienda**\n* **Supporto marketing e strategico** per la generazione di nuovi contatti e il mantenimento della clientela acquisita.\n* **Percorso di crescita reale**: dalla gestione di clienti residenziali alla trattativa con aziende e realtà industriali.\n* **Formazione tecnica e commerciale continua**, sia in aula che sul campo.\n* **Autonomia organizzativa** nella gestione dell’agenda e del territorio.\n* **Ambiente giovane e dinamico**\n\n**Perché scegliere questa opportunità**\n\n\nEntra in una realtà concreta, solida e riconosciuta anche dai grandi player del mercato.  \n\nSe ti riconosci in questa descrizione, inviaci il tuo CV e raccontaci perché sei la persona giusta.",
    "company_industry":null,
    "company_url":"https:\/\/it.indeed.com\/cmp\/Salesvalley",
    "company_logo":null,
    "company_url_direct":null,
    "company_addresses":null,
    "company_num_employees":null,
    "company_revenue":null,
    "company_description":null,
    "skills":null,
    "experience_range":null,
    "company_rating":null,
    "company_reviews_count":null,
    "vacancy_count":null,
    "work_from_home_type":null,
    "search_term":"persona qualificata"
  },
  {
    "id":"in-4d898f03460bdd3e",
    "site":"indeed",
    "job_url":"https:\/\/it.indeed.com\/viewjob?jk=4d898f03460bdd3e",
    "job_url_direct":"https:\/\/app.ncoreplat.com\/jobsharingredirect\/789036\/quality-assurance-consultant-it\/frk-ops-quality-assurance?type=2&platform=29&sharing=5057361&source=Indeed",
    "title":"Quality Assurance Consultant",
    "company":"JSB Solutions srl",
    "location":"Sesto Fiorentino, TOS, IT",
    "date_posted":1774569600000,
    "job_type":null,
    "salary_source":null,
    "interval":null,
    "min_amount":null,
    "max_amount":null,
    "currency":null,
    "is_remote":true,
    "job_level":null,
    "job_function":null,
    "listing_type":null,
    "emails":null,
    "description":"**JSB Solutions** – azienda leader nei servizi life sciences con focus su consulenza, gestione studi clinici e sviluppo software \\- ricerca per il potenziamento del proprio organico una figura di **Quality Assurance Consultant** (*JSB.FRK.26\\.005*) da inserire all'interno della propria divisione di **Assicurazione Qualità**.\n\n\n**Chi siamo**: con quattro sedi operative in Italia (Firenze, Parma, Milano e Roma), supportiamo le principali aziende farmaceutiche nei processi di compliance, di gestione di studi clinici e sviluppo piattaforme software combinando expertise tecnico e approccio consulenziale.  \n\n  \n\n**Il ruolo**: Il candidato ideale ha conseguito una laurea in discipline scientifiche ed ha maturato **almeno 3 anni di esperienza in Quality Assurance**, preferibilmente in aziende di manifattura farmaceutica.  \n\n  \n\n**Responsabilità principali:**\n\n\n* **gestione del Sistema Qualità in ambito GMP**, garantendo il rispetto delle normative vigenti e delle procedure aziendali e fornendo supporto al miglioramento continuo del sistema qualità;\n* **supporto durante ispezioni e audit da parte di clienti, enti regolatori e terze parti**, contribuendo alla preparazione della documentazione, alla gestione delle richieste degli auditor e al follow\\-up delle eventuali osservazioni emerse;\n* **stesura, revisione e gestione della documentazione di qualità**, inclusi SOP, istruzioni operative, report di qualità, procedure di sistema e documentazione correlata, assicurandone la conformità ai requisiti normativi e agli standard aziendali;\n* **gestione di non conformità, reclami, deviazioni e CAPA**, coordinando le attività di investigazione, analisi delle cause radice e definizione delle azioni correttive e preventive, monitorando l’efficacia e il completamento;\n* **preparazione ed erogazione di attività di training**, finalizzate alla diffusione della cultura della qualità e alla corretta applicazione delle procedure e delle normative GMP da parte del personale coinvolto;\n* **supporto ai clienti e interfaccia continua durante la gestione delle commesse**, garantendo un confronto costante per l’allineamento sui requisiti di qualità, la gestione di eventuali criticità e il monitoraggio dello stato delle attività, assicurando trasparenza, tempestività e conformità agli standard concordati.\n\n**Requisiti richiesti dal ruolo:**\n\n\n* almeno 3 anni di esperienza in ambito Quality Assurance;\n* esperienza nella redazione di documentazione di qualità (ad es. SOP, PQR, QTA, risk analisi);\n* laurea in discipline scientifiche;\n* ottima conoscenza delle normative GMP e degli standard di qualità applicabili;\n* ottima conoscenza della lingua inglese;\n* attitudine a lavorare in ambienti dinamici ed in rapida evoluzione;\n* elevate capacità comunicative con clienti esterni e interni.\n\n**Offriamo:**\n\n\n* inserimento in un contesto professionale stimolante;\n* formazione continua su tecnologie e normative di settore;\n* opportunità di crescita professionale;\n* partecipazione a progetti internazionali.\n\n**Sede di lavoro:** Sesto Fiorentino.\n\n\n**Modalità di lavoro:** formula mista ufficio \\- smart working.",
    "company_industry":null,
    "company_url":"https:\/\/it.indeed.com\/cmp\/Jsb-Solutions-Srl",
    "company_logo":null,
    "company_url_direct":null,
    "company_addresses":null,
    "company_num_employees":"Decline to state",
    "company_revenue":"Decline to state",
    "company_description":null,
    "skills":null,
    "experience_range":null,
    "company_rating":null,
    "company_reviews_count":null,
    "vacancy_count":null,
    "work_from_home_type":null,
    "search_term":"GMP compliance"
  },
  {
    "id":"in-acd778875799346a",
    "site":"indeed",
    "job_url":"https:\/\/it.indeed.com\/viewjob?jk=acd778875799346a",
    "job_url_direct":"https:\/\/careers.harris.com\/job\/-\/-\/4832\/93152072272",
    "title":"Product and Reliability Engineer",
    "company":"L3Harris",
    "location":"Bologna, EMI, IT",
    "date_posted":1774396800000,
    "job_type":null,
    "salary_source":null,
    "interval":null,
    "min_amount":null,
    "max_amount":null,
    "currency":null,
    "is_remote":false,
    "job_level":null,
    "job_function":null,
    "listing_type":null,
    "emails":null,
    "description":"L3Harris is dedicated to recruiting and developing high\\-performing talent who are passionate about what they do. Our employees are unified in a shared dedication to our customers’ mission and quest for professional growth. L3Harris provides an inclusive, engaging environment designed to empower employees and promote work\\-life success. Fundamental to our culture is an unwavering focus on values, dedication to our communities, and commitment to excellence in everything we do.\n\n\nL3Harris is the Trusted Disruptor in defense tech. With customers’ mission\\-critical needs always in mind, our employees deliver end\\-to\\-end technology solutions connecting the space, air, land, sea and cyber domains in the interest of national security.\n\n**Job Title – Product and Reliability Engineer**\n\n**Job Location – Italy**\n\n**Job ID – 35152**\n\n **About this opportunity and L3Harris Italy**\n\n\nThe Product \\& Reliability Engineer role is dedicated to ensuring Products and Systems comply with Customer and Technical Requirements, with specific focus on those requiring a Qualification via Test. **What the role will involve**\n\n\nThe responsibilities of your role will include the following:\n\n* Being responsible for Product Qualifications: defines and organizes laboratory tests (EMC, Electrical Safety, Shock and Vibration, Noise, etc.) in compliance with applicable technical standards and customer requirements\n* Participates, in collaboration with the Engineering Area, in defining and validating project requirements\n* Participates in preparing technical files and in obtaining product certifications in collaboration with the Technical Office and external laboratories\/bodies, following their life cycles, from submission to their periodic maintenance\n* Manages product regulatory compliance (Guidelines, Directives, Standards, etc.) over the time\n* Together with the Engineering Area, the resource responsible for defining, developing, and maintaining testing procedures and technical specifications\n* Collaborates in managing the internal testing laboratory and performs tests with its equipment when part of testing or qualifications activities\n* Evaluates and proposes predictive and\/or other non\\-destructive testing methodologies useful for identifying and isolating reliability issues\n* Participates in testing new systems, when necessary, to verify compliance with functional specifications\n* Participates in Failure Analyses and 8D Reports, overseeing their preparation when necessary\n* Provides input for a proper risks management, identifying and addressing aspects that could negatively impact system operation\n* Provides technical support to Production or Engineering areas, when necessary\n\n **What you’ll bring**\n\n\nThe role requires the following experience and skills:\n\n* Master's degree in Electronic Engineering\n* Consolidated experience with product standards and testing\n* Experience managing product qualifications and certifications, including technical dossiers\n* Knowledge of SAP management software is preferred\n* Knowledge of quality planning\/management tools\/systems (APQP) is preferred",
    "company_industry":null,
    "company_url":"https:\/\/it.indeed.com\/cmp\/L3harris",
    "company_logo":"https:\/\/d2q79iu7y748jz.cloudfront.net\/s\/_squarelogo\/256x256\/6a6c9f075b48a5898354e5f275c43a33",
    "company_url_direct":"https:\/\/www.l3harris.com",
    "company_addresses":"Melbourne, FL",
    "company_num_employees":"10,000+",
    "company_revenue":"more than $10B (USD)",
    "company_description":"At L3Harris, we are proud to employ innovators and problem solvers dedicated to delivering mission critical solutions our customers on the front lines depend on. Learn more at.L3Harris.com\/careers.",
    "skills":null,
    "experience_range":null,
    "company_rating":null,
    "company_reviews_count":null,
    "vacancy_count":null,
    "work_from_home_type":null,
    "search_term":"regulatory submission"
  },
  {
    "id":"in-0b95a14278544c4b",
    "site":"indeed",
    "job_url":"https:\/\/it.indeed.com\/viewjob?jk=0b95a14278544c4b",
    "job_url_direct":"https:\/\/career2.successfactors.eu\/career?career%5fns=job%5flisting&company=datalogics&navBarLevel=JOB%5fSEARCH&rcm%5fsite%5flocale=en%5fUS&career_job_req_id=10959&selected_lang=en_US&jobAlertController_jobAlertId=&jobAlertController_jobAlertName=&browserTimeZone=America\/Chicago&_s.crb=fRSF5%2bfCZVhmtToZm%2f1IlJTO4tLReTat9Nirm4%2b%2fnKQ%3d",
    "title":"SAP Controlling Business Analyst",
    "company":"Datalogic",
    "location":"Calderara di Reno, EMI, IT",
    "date_posted":1774224000000,
    "job_type":null,
    "salary_source":null,
    "interval":null,
    "min_amount":null,
    "max_amount":null,
    "currency":null,
    "is_remote":false,
    "job_level":null,
    "job_function":null,
    "listing_type":null,
    "emails":null,
    "description":"**Job Description**\n-------------------\n\n\n\nDatalogic Group is looking for a SAP Controlling Business Analyst to join the Global Demand Management and ICT Applications Team within the Information and Communications Technology Department.\nThis position will play a key role in supporting and improving the company internal financial and cost management processes at global level and will be based in the HQ in Lippo di Calderara (BO).  \n\n\nROLE MISSION\nThe SAP Controlling Business Analyst will be responsible for analyzing, designing, and continuously optimizing business processes related to cost control, internal reporting, and financial forecasting, with a specific focus mainly on the SAP Controlling (CO) module and related tools across the Datalogic Group.\nThis role is a strategic link between business and IT, ensuring that financial and controlling requirements are effectively translated into functional SAP configurations and digital solutions that support informed decision\\-making.  \n\n\nKEY RESPONSIBILITIES\nCollaborate with business stakeholders to gather and analyze requirements related to financial control, cost tracking, and internal reporting.\no Identify opportunities to improve efficiency, accuracy, and usability of cost and financial management processes.\no Design solutions, configure and customize SAP CO and PS modules (Cost Center and Profit Center Accounting, Internal Order Management, Standard Costs and Material Ledger Management, WBS, etc.) to align with business requirements.\no Coordinate external consultant support to Project or important Change Request initiatives on Controlling Area.\no Support the improvement of SAP CO and PS for regulatory compliance ensuring that the system meets all user and requirements.\no Collaborate with Business Intelligence team in developing reports to support business decisions, providing analytical support in the areas of cost tracking, profitability analysis, and financial forecasting.\no Participate in cross\\-functional projects, contributing on analyzing and explaining on SAP controlling domain to broader digital transformation initiatives.  \n\n\n*Bachelor's or Master's degree in Finance, Accounting, Information Technology, or a related field.*  \n\n*Fluent in English.*  \n\n*Minimum 3 years of proven experience in SAP CO and PS modules configuration, implementation, and support.*  \n\n\n* Solid knowledge and understanding of financial processes and cost management.\n* Familiarity with other SAP modules (FI, PP, MM, SD) and reporting tools like SAP BW, PowerBI, QlikView would be considered a plus.\n* Experience with SAP S\/4HANA is a strong plus",
    "company_industry":null,
    "company_url":"https:\/\/it.indeed.com\/cmp\/Datalogic",
    "company_logo":null,
    "company_url_direct":"https:\/\/www.datalogic.com\/eng\/index.html",
    "company_addresses":null,
    "company_num_employees":null,
    "company_revenue":null,
    "company_description":"",
    "skills":null,
    "experience_range":null,
    "company_rating":null,
    "company_reviews_count":null,
    "vacancy_count":null,
    "work_from_home_type":null,
    "search_term":"regulatory compliance"
  },
  {
    "id":"li-4391580239",
    "site":"linkedin",
    "job_url":"https:\/\/www.linkedin.com\/jobs\/view\/4391580239",
    "job_url_direct":null,
    "title":"Quality Assurance Engineer",
    "company":"EPM Scientific",
    "location":"Mirandola, Emilia-Romagna, Italy",
    "date_posted":1774569600000,
    "job_type":null,
    "salary_source":null,
    "interval":null,
    "min_amount":null,
    "max_amount":null,
    "currency":null,
    "is_remote":false,
    "job_level":"",
    "job_function":null,
    "listing_type":null,
    "emails":null,
    "description":null,
    "company_industry":null,
    "company_url":"https:\/\/uk.linkedin.com\/company\/epm-scientific",
    "company_logo":null,
    "company_url_direct":null,
    "company_addresses":null,
    "company_num_employees":null,
    "company_revenue":null,
    "company_description":null,
    "skills":null,
    "experience_range":null,
    "company_rating":null,
    "company_reviews_count":null,
    "vacancy_count":null,
    "work_from_home_type":null,
    "search_term":"regulatory compliance"
  }
]